<?xml version="1.0" ?>
<Benchmark terminals="50" timeLimit="180" env="2D/Maze_planar_env.dae" robot="2D/car2_planar_robot.dae" runs="10">
	<Sstar ordering="UB - LB" informed="True">
		<Output spanningTreeLength="594.425" tourCost="1174.012" timeTaken="174.649" pruned="1110" costOverTime="{10.0831: 615.7555, 24.2149: 615.7555, 25.338: 606.2169, 35.4748: 606.2169, 37.0882: 602.9348, 46.5077: 602.9348, 48.9713: 601.4841, 58.4369: 601.4841, 60.9708: 599.8355, 70.4154: 599.8355, 73.1782: 598.8902, 82.6708: 598.8902, 85.7513: 597.8381, 95.2875: 597.8381, 99.2786: 595.8735, 108.8695: 595.8735, 113.0423: 595.8554, 122.7106: 595.8554, 128.2192: 595.5764, 137.9063: 595.5764, 143.4688: 594.6214, 153.2002: 594.6214, 158.4742: 594.4732, 168.1388: 594.4732, 174.4736: 594.4246, 174.6457: 594.4246}"/>
		<Output spanningTreeLength="593.351" tourCost="1172.076" timeTaken="173.481" pruned="1113" costOverTime="{9.9078: 614.5569, 24.8375: 614.5569, 25.8925: 606.8892, 36.0539: 606.8892, 37.6684: 603.0457, 47.0747: 603.0457, 49.4281: 599.1097, 58.9164: 599.1097, 61.6758: 597.8783, 71.1749: 597.8783, 73.8966: 597.3718, 83.3863: 597.3718, 86.5881: 595.7994, 109.5542: 595.7994, 113.9927: 595.2253, 123.595: 595.2253, 128.5112: 595.1058, 138.1748: 595.1058, 142.9377: 593.4979, 152.5933: 593.4979, 157.6744: 593.3982, 167.3619: 593.3982, 173.3122: 593.351, 173.476: 593.351}"/>
		<Output spanningTreeLength="592.66" tourCost="1170.674" timeTaken="172.703" pruned="1115" costOverTime="{9.878: 628.3094, 24.1911: 628.3094, 25.4215: 618.925, 35.6592: 618.925, 37.275: 604.5619, 46.8091: 604.5619, 48.9391: 600.6866, 58.4344: 600.6866, 60.7783: 600.2772, 70.1975: 600.2772, 72.8142: 598.2795, 82.3144: 598.2795, 85.9562: 597.1117, 95.4595: 597.1117, 99.3402: 596.2395, 108.8701: 596.2395, 113.2345: 595.0594, 122.7761: 595.0594, 127.0935: 595.0553, 136.7408: 595.0553, 141.3284: 594.6418, 151.0432: 594.6418, 156.9421: 593.697, 166.6404: 593.697, 172.5246: 592.6599, 172.6987: 592.6599}"/>
		<Output spanningTreeLength="591.671" tourCost="1168.8" timeTaken="173.353" pruned="1113" costOverTime="{9.8332: 613.0742, 23.6333: 613.0742, 24.9626: 605.7384, 35.2635: 605.7384, 36.9779: 602.5711, 46.4181: 602.5711, 48.3716: 600.6153, 57.8014: 600.6153, 60.2164: 599.8592, 69.6755: 599.8592, 72.4375: 597.041, 81.942: 597.041, 85.1546: 594.9346, 94.6882: 594.9346, 98.3764: 594.5853, 108.0888: 594.5853, 112.6289: 593.9374, 122.2435: 593.9374, 127.1548: 592.7415, 151.6925: 592.7415, 157.5885: 591.8033, 167.309: 591.8033, 173.2054: 591.6708, 173.35: 591.6708}"/>
		<Output spanningTreeLength="591.883" tourCost="1168.954" timeTaken="174.252" pruned="1112" costOverTime="{9.9616: 613.7682, 24.6599: 613.7682, 25.8729: 603.7877, 36.3084: 603.7877, 37.9186: 598.3498, 47.342: 598.3498, 49.3759: 596.645, 58.8185: 596.645, 61.1243: 596.0572, 70.5976: 596.0572, 73.3394: 594.6243, 82.8205: 594.6243, 86.1297: 593.113, 95.7002: 593.113, 99.7708: 592.9903, 109.3762: 592.9903, 113.7507: 592.8525, 123.3822: 592.8525, 127.847: 592.6611, 137.5002: 592.6611, 142.9737: 591.9323, 167.682: 591.9323, 174.064: 591.8827, 174.2455: 591.8827}"/>
		<Output spanningTreeLength="592.44" tourCost="1169.96" timeTaken="172.053" pruned="1113" costOverTime="{9.8942: 613.6296, 24.6986: 613.6296, 25.787: 606.5194, 35.734: 606.5194, 37.2092: 601.6743, 46.5834: 601.6743, 48.7377: 598.7911, 58.1667: 598.7911, 60.69: 598.6374, 70.1122: 598.6374, 72.7738: 598.3692, 82.2263: 598.3692, 85.3435: 596.8415, 94.8473: 596.8415, 98.6305: 595.3607, 108.1576: 595.3607, 112.0366: 594.6108, 121.5884: 594.6108, 125.9123: 594.1605, 135.5766: 594.1605, 141.0942: 593.093, 150.7364: 593.093, 156.4907: 592.5841, 166.2546: 592.5841, 171.9299: 592.4401, 172.0493: 592.4401}"/>
		<Output spanningTreeLength="591.698" tourCost="1169.32" timeTaken="185.137" pruned="1113" costOverTime="{9.7588: 615.4437, 22.8916: 615.4437, 23.9377: 601.7303, 33.9513: 601.7303, 35.3777: 599.2923, 44.7645: 599.2923, 46.8227: 598.8714, 56.2171: 598.8714, 58.734: 597.3191, 68.2529: 597.3191, 71.1008: 596.58, 80.5427: 596.58, 83.6272: 596.5042, 93.0831: 596.5042, 96.5356: 593.7873, 106.1305: 593.7873, 110.3649: 592.9245, 134.2667: 592.9245, 139.1903: 592.6075, 148.7706: 592.6075, 153.7627: 592.4039, 163.5279: 592.4039, 169.6045: 592.1838, 179.292: 592.1838}"/>
		<Output spanningTreeLength="591.775" tourCost="1168.574" timeTaken="172.631" pruned="1112" costOverTime="{9.8231: 621.7365, 22.6974: 621.7365, 23.926: 618.9606, 33.7468: 618.9606, 35.3746: 602.3145, 44.7945: 602.3145, 46.8283: 597.4285, 56.2309: 597.4285, 58.8228: 596.1836, 68.2503: 596.1836, 71.3818: 595.6037, 80.868: 595.6037, 84.4723: 594.5936, 93.9847: 594.5936, 97.6763: 593.7476, 107.2008: 593.7476, 111.4331: 593.2217, 121.0761: 593.2217, 125.8511: 591.9871, 150.1176: 591.9871, 155.9576: 591.9633, 165.7049: 591.9633, 172.509: 591.7752, 172.6281: 591.7752}"/>
		<Output spanningTreeLength="592.3" tourCost="1170.206" timeTaken="172.815" pruned="1114" costOverTime="{9.8427: 616.1855, 23.8193: 616.1855, 24.8028: 609.0776, 34.6834: 609.0776, 36.9708: 601.4428, 46.4194: 601.4428, 48.6119: 599.236, 58.0116: 599.236, 60.9092: 598.3282, 70.3628: 598.3282, 72.9567: 598.2077, 82.5454: 598.2077, 86.1717: 597.0897, 95.7349: 597.0897, 99.4403: 594.0503, 109.0585: 594.0503, 113.4542: 593.4611, 123.0185: 593.4611, 127.6321: 593.2218, 137.244: 593.2218, 142.3635: 593.0461, 152.0454: 593.0461, 157.3806: 592.4793, 167.0447: 592.4793, 172.6947: 592.3004, 172.8113: 592.3004}"/>
		<Output spanningTreeLength="593.747" tourCost="1172.878" timeTaken="183.084" pruned="1109" costOverTime="{10.0544: 612.7015, 24.4984: 612.7015, 26.416: 606.1709, 37.2723: 606.1709, 39.5473: 603.5515, 49.1623: 603.5515, 54.2444: 601.4676, 64.3599: 601.4676, 67.373: 598.7843, 76.9246: 598.7843, 81.5436: 598.464, 90.9855: 598.464, 93.6984: 597.4621, 103.2769: 597.4621, 107.3087: 596.4465, 116.8179: 596.4465, 120.0718: 594.379, 129.5995: 594.379, 133.7769: 594.0027, 143.459: 594.0027, 148.7252: 593.9854, 158.561: 593.9854, 165.1183: 593.7468, 176.2146: 593.7468}"/>
	</Sstar>
	<PotentiallyOptimal spanningTreeLength="600.259" tourCost="953.83" timeTaken="180.01"/>
	<LowerBound spanningTreeLength="490.7" tourCost="981.4" timeTaken="1"/>
	<IncrementalSstar>
		<Output spanningTreeLength="592.665" tourCost="1170.591" timeTaken="174.572" pruned="1111" costOverTime="{9.9574: 622.9424, 25.3507: 622.9424, 26.6512: 616.9396, 36.9414: 616.9396, 38.6313: 614.4385, 48.1646: 614.4385, 50.2669: 600.9497, 59.7898: 600.9497, 62.7116: 599.1017, 72.1801: 599.1017, 74.837: 597.2168, 84.3567: 597.2168, 88.1976: 596.6143, 97.7603: 596.6143, 101.2805: 594.733, 110.8702: 594.733, 115.1237: 593.8435, 124.6938: 593.8435, 129.1599: 593.3387, 138.7492: 593.3387, 143.7835: 592.6925, 153.5101: 592.6925, 158.7371: 592.6649, 174.5686: 592.6649}"/>
		<Output spanningTreeLength="590.688" tourCost="1166.86" timeTaken="175.079" pruned="1114" costOverTime="{9.8559: 626.1408, 24.9318: 626.1408, 26.1724: 620.9438, 36.3775: 620.9438, 38.0629: 608.1249, 47.5: 608.1249, 49.4291: 605.1036, 58.8382: 605.1036, 61.2321: 602.6838, 70.7519: 602.6838, 73.7742: 602.2311, 83.2539: 602.2311, 86.8885: 598.1644, 96.4692: 598.1644, 100.6343: 596.6514, 110.2293: 596.6514, 114.6877: 595.7127, 124.3574: 595.7127, 129.2145: 593.806, 138.8524: 593.806, 143.9315: 591.7959, 153.626: 591.7959, 159.2131: 591.4596, 168.9187: 591.4596, 174.9336: 590.688, 175.0761: 590.688}"/>
		<Output spanningTreeLength="590.14" tourCost="1165.667" timeTaken="172.418" pruned="1108" costOverTime="{9.906: 631.4005, 24.7552: 631.4005, 26.0207: 602.5302, 36.1791: 602.5302, 37.7226: 597.7998, 47.1201: 597.7998, 49.1607: 596.7763, 58.6102: 596.7763, 61.3339: 596.0349, 70.8527: 596.0349, 74.1214: 594.8914, 83.6249: 594.8914, 87.4475: 594.346, 96.9341: 594.346, 100.4608: 593.8922, 109.957: 593.8922, 113.4245: 592.5777, 122.9453: 592.5777, 127.5491: 592.144, 137.1877: 592.144, 142.0737: 591.4775, 151.7607: 591.4775, 156.9919: 590.2214, 166.7004: 590.2214, 172.2909: 590.1398, 172.4152: 590.1398}"/>
		<Output spanningTreeLength="594.74" tourCost="1174.349" timeTaken="172.411" pruned="1110" costOverTime="{9.8406: 631.3443, 23.441: 631.3443, 24.5461: 614.8388, 34.5418: 614.8388, 36.1874: 611.8868, 45.6096: 611.8868, 47.5778: 608.9144, 57.0022: 608.9144, 59.5338: 606.939, 69.1063: 606.939, 72.1004: 604.9091, 81.5916: 604.9091, 84.8907: 604.2495, 94.3865: 604.2495, 98.0078: 604.1723, 107.6028: 604.1723, 111.9777: 594.9633, 121.6089: 594.9633, 125.9574: 594.8865, 150.7401: 594.8865, 156.5652: 594.744, 166.3809: 594.744, 172.2789: 594.7403, 172.4072: 594.7403}"/>
		<Output spanningTreeLength="592.282" tourCost="1169.173" timeTaken="180.103" pruned="1109" costOverTime="{9.8143: 634.4627, 23.4809: 634.4627, 24.6147: 629.349, 34.612: 629.349, 36.4681: 619.9019, 45.9504: 619.9019, 48.2363: 604.5442, 57.7312: 604.5442, 60.1475: 601.7308, 69.5512: 601.7308, 72.0374: 599.6446, 81.4809: 599.6446, 84.4194: 597.9479, 93.9443: 597.9479, 97.6239: 596.4371, 107.2139: 596.4371, 111.0205: 595.5129, 120.5905: 595.5129, 125.8052: 593.0739, 135.4263: 593.0739, 140.4125: 592.9626, 149.9936: 592.9626, 154.9593: 592.7192, 164.6396: 592.7192, 170.2795: 592.2821, 179.5461: 592.2821}"/>
		<Output spanningTreeLength="591.806" tourCost="936.487" timeTaken="174.13" pruned="1112" costOverTime="{9.8894: 638.9841, 23.8573: 638.9841, 25.0717: 620.7179, 35.1221: 620.7179, 36.7646: 615.5696, 46.1859: 615.5696, 48.1598: 598.9433, 57.606: 598.9433, 59.9878: 597.652, 69.4401: 597.652, 72.378: 596.4637, 81.9129: 596.4637, 85.5524: 596.1051, 95.196: 596.1051, 99.2605: 595.723, 108.909: 595.723, 113.082: 595.046, 122.6726: 595.046, 127.137: 593.2391, 136.8022: 593.2391, 141.7013: 592.8494, 151.4261: 592.8494, 157.9751: 592.1957, 167.7789: 592.1957, 173.9891: 591.8062, 174.1267: 591.8062}"/>
		<Output spanningTreeLength="589.938" tourCost="1165.286" timeTaken="185.614" pruned="1115" costOverTime="{9.8804: 615.9337, 24.0443: 615.9337, 25.2447: 606.6332, 35.207: 606.6332, 36.6803: 600.5962, 46.0755: 600.5962, 48.0285: 597.1212, 57.4418: 597.1212, 60.1789: 595.3071, 69.6474: 595.3071, 72.5289: 594.6696, 81.9845: 594.6696, 85.0645: 593.8943, 107.5547: 593.8943, 111.1441: 592.8228, 120.6712: 592.8228, 124.6711: 591.7495, 134.2673: 591.7495, 139.4921: 591.2696, 149.06: 591.2696, 153.9008: 590.6587, 163.5607: 590.6587, 169.337: 589.9549, 179.0887: 589.9549}"/>
		<Output spanningTreeLength="591.367" tourCost="1168.045" timeTaken="171.541" pruned="1113" costOverTime="{9.8027: 610.9299, 23.1809: 610.9299, 24.3073: 603.2784, 34.1711: 603.2784, 35.6454: 600.626, 45.0024: 600.626, 47.3892: 599.5155, 56.8157: 599.5155, 59.1351: 598.4346, 68.5726: 598.4346, 71.3538: 596.5487, 80.8658: 596.5487, 84.1294: 594.3461, 93.6248: 594.3461, 97.178: 593.5511, 106.7231: 593.5511, 111.197: 592.6185, 136.0012: 592.6185, 141.1777: 592.0771, 150.808: 592.0771, 156.0051: 591.4815, 165.7653: 591.4815, 171.4341: 591.367, 171.5384: 591.367}"/>
		<Output spanningTreeLength="591.038" tourCost="937.904" timeTaken="172.395" pruned="1114" costOverTime="{9.9096: 612.3327, 23.1893: 612.3327, 24.4417: 605.5747, 34.3398: 605.5747, 36.2915: 598.4815, 45.7214: 598.4815, 47.9: 595.3486, 57.3612: 595.3486, 60.3806: 594.5003, 69.8271: 594.5003, 73.1698: 594.3582, 82.7143: 594.3582, 86.2771: 593.4116, 95.8271: 593.4116, 99.7916: 592.7117, 109.6933: 592.7117, 116.0007: 592.2826, 132.3585: 592.2826, 150.0537: 591.9289, 162.8064: 591.9289, 172.1504: 591.0375, 172.3896: 591.0375}"/>
		<Output spanningTreeLength="591.655" tourCost="1168.349" timeTaken="173.888" pruned="1112" costOverTime="{9.8351: 622.2144, 23.9089: 622.2144, 25.0931: 606.8184, 35.1749: 606.8184, 37.8147: 603.9279, 47.216: 603.9279, 49.0298: 599.5577, 58.5217: 599.5577, 62.2669: 595.1224, 84.1846: 595.1224, 87.4314: 593.5741, 97.0482: 593.5741, 100.5175: 593.4287, 110.0591: 593.4287, 114.1697: 592.9984, 123.758: 592.9984, 128.3816: 592.14, 137.9959: 592.14, 142.6673: 592.0824, 152.2927: 592.0824, 158.0249: 591.6581, 167.7036: 591.6581, 173.7612: 591.6554, 173.884: 591.6554}"/>
	</IncrementalSstar>
</Benchmark>
