<?xml version="1.0" ?>
<Benchmark terminals="10" timeLimit="600" env="3D/Home_env.dae" robot="3D/Home_robot.dae" runs="50" seed="1234">
	<PotentiallyOptimal/>
	<LowerBound spanningTreeLength="1172.03" tourCost="2344.06" timeTaken="1"/>
	<Ripple>
		<Output spanningTreeLength="1269.985" tourCost="2200.88" timeTaken="595.188" pruned="31" ellipsesRemaining="9" costOverTime="{65.6971: 1332.2331, 75.4008: 1332.2331, 75.4009: 1330.0221, 94.4151: 1324.4233, 113.7677: 1324.3353, 123.7211: 1323.6442, 123.7212: 1322.4889, 133.3634: 1321.4412, 162.5688: 1321.4412, 162.5689: 1319.8516, 172.4084: 1319.3021, 192.0703: 1319.3021, 192.0704: 1318.6206, 211.9871: 1317.6607, 232.2709: 1308.6268, 232.271: 1302.9674, 325.0401: 1299.0916, 378.6005: 1299.0603, 389.3922: 1294.7298, 478.164: 1291.7444, 478.1641: 1284.3586, 512.6072: 1270.3202, 583.1309: 1269.9851, 595.1852: 1269.9851}"/>
		<Output spanningTreeLength="1274.073" tourCost="1965.121" timeTaken="596.506" pruned="31" ellipsesRemaining="9" costOverTime="{26.0136: 1775.7516, 35.5015: 1716.5723, 35.5044: 1695.8113, 44.7313: 1695.8113, 44.7314: 1627.5951, 44.7315: 1627.5856, 44.7318: 1586.9399, 53.9443: 1583.9278, 53.9446: 1570.3747, 63.2059: 1566.3415, 63.2063: 1566.3415, 63.2064: 1563.2645, 72.484: 1563.2645, 72.4841: 1556.797, 72.4842: 1556.1269, 72.4843: 1556.1269, 72.4869: 1540.5248, 82.1788: 1540.5248, 82.1789: 1419.5451, 82.179: 1415.7409, 91.6776: 1363.7584, 101.0823: 1341.7077, 110.6503: 1337.4899, 120.3709: 1335.8334, 130.1581: 1326.2438, 159.6479: 1286.2775, 169.7068: 1286.2775, 169.7069: 1285.8721, 189.3776: 1283.9608, 199.3722: 1283.817, 323.707: 1283.817, 323.7071: 1282.0935, 355.6498: 1281.9381, 467.6086: 1280.959, 502.0124: 1275.5604, 525.2472: 1274.8985, 536.8172: 1274.7975, 560.4356: 1274.073, 596.5033: 1274.073}"/>
		<Output spanningTreeLength="1276.07" tourCost="2182.587" timeTaken="596.772" pruned="31" ellipsesRemaining="9" costOverTime="{25.9015: 2270.6322, 35.0711: 2270.6322, 35.0798: 2245.7746, 35.0951: 2121.7254, 44.3517: 2121.7254, 44.3518: 2082.5263, 53.5994: 2074.063, 53.6026: 2069.4187, 62.8803: 2069.4187, 62.8804: 2049.7684, 62.881: 2033.2552, 81.7422: 2001.3624, 91.258: 2001.3624, 91.2581: 1999.6723, 139.5233: 1999.6723, 139.5234: 1998.9383, 149.2274: 1996.7184, 149.228: 1995.5923, 159.4348: 1992.5527, 169.1892: 1991.178, 179.0144: 1978.9757, 198.8725: 1396.4819, 219.0297: 1362.4158, 229.0974: 1348.8063, 249.4231: 1346.5621, 270.1313: 1346.5621, 270.1314: 1344.5617, 280.4633: 1344.5617, 280.4634: 1339.1549, 290.8765: 1339.1549, 290.8766: 1308.7307, 312.4522: 1304.0568, 365.9054: 1304.0568, 365.9055: 1291.8439, 409.8215: 1280.1329, 454.9262: 1276.07, 596.7696: 1276.07}"/>
		<Output spanningTreeLength="1255.663" tourCost="1931.111" timeTaken="593.534" pruned="32" ellipsesRemaining="8" costOverTime="{12.9218: 2248.1438, 22.1075: 2248.1438, 22.1157: 2179.2602, 22.1319: 2147.1882, 31.429: 2147.1882, 31.4291: 2143.9328, 31.4297: 2088.0054, 40.6121: 2088.0054, 40.6122: 2078.8421, 40.6127: 2042.9188, 50.0828: 2042.9188, 50.0829: 2036.6193, 50.0839: 1992.446, 68.8839: 1992.446, 68.884: 1990.5702, 68.8845: 1986.136, 78.2352: 1985.2114, 87.6378: 1985.2114, 87.6379: 1984.3138, 106.6137: 1359.8439, 125.9401: 1359.8439, 125.9402: 1359.0228, 136.0399: 1323.9069, 136.04: 1323.0467, 146.0594: 1314.8496, 195.5571: 1301.5381, 205.5212: 1299.9208, 215.4823: 1299.2845, 225.6049: 1297.8265, 236.4281: 1296.5756, 288.7258: 1294.7168, 299.1012: 1293.4036, 320.7728: 1293.4036, 320.7729: 1291.8614, 331.3694: 1270.6603, 342.5937: 1270.6603, 342.5938: 1266.6184, 342.5939: 1265.7028, 431.1098: 1256.3337, 453.4965: 1256.107, 498.9125: 1256.107, 498.9126: 1255.6625, 593.5319: 1255.6625}"/>
		<Output spanningTreeLength="1261.036" tourCost="1948.276" timeTaken="601.558" pruned="32" ellipsesRemaining="8" costOverTime="{39.4149: 1626.3887, 39.415: 1625.969, 48.7821: 1625.969, 48.79: 1625.9574, 58.1153: 1625.9574, 58.1154: 1388.4732, 58.1155: 1388.2108, 67.4378: 1385.6918, 67.4379: 1372.307, 76.8011: 1372.307, 76.8012: 1335.86, 86.6038: 1335.86, 86.6039: 1333.1533, 115.1596: 1333.1533, 115.1597: 1328.2344, 124.7567: 1328.2344, 124.7568: 1323.7796, 134.5289: 1291.2064, 203.4359: 1289.9225, 203.436: 1284.5217, 223.4384: 1279.026, 244.0917: 1269.7791, 404.3277: 1269.3104, 449.4098: 1269.3104, 449.4099: 1268.9653, 471.9093: 1264.5965, 471.9094: 1261.2373, 541.3634: 1261.0356, 598.4164: 1261.0356}"/>
		<Output spanningTreeLength="1266.44" tourCost="2167.965" timeTaken="600.556" pruned="32" ellipsesRemaining="8" costOverTime="{12.9348: 1552.2024, 12.9373: 1549.6908, 22.0846: 1549.6908, 22.0926: 1547.1741, 22.0927: 1493.9525, 31.2955: 1493.9525, 31.2956: 1409.6777, 40.5336: 1409.6777, 40.5337: 1391.6277, 50.0402: 1390.4195, 59.3138: 1390.4195, 59.3139: 1356.9863, 68.7491: 1356.9863, 68.7492: 1350.9616, 78.0677: 1350.1933, 78.0678: 1349.3243, 87.5101: 1349.3243, 87.5102: 1338.3228, 87.5103: 1336.9102, 96.8932: 1336.9102, 96.8933: 1335.9614, 106.2806: 1332.1303, 115.8103: 1332.1303, 115.8104: 1326.7318, 115.8105: 1324.7662, 125.3355: 1319.5808, 125.3356: 1317.7801, 134.9545: 1310.6341, 154.2283: 1310.6341, 154.2284: 1308.4429, 173.9231: 1307.3417, 193.6668: 1307.3417, 193.6669: 1301.8376, 193.667: 1300.2996, 203.915: 1300.2996, 203.9151: 1300.0519, 213.9065: 1300.0519, 213.9066: 1298.5736, 234.1792: 1289.0546, 275.5564: 1288.4449, 286.146: 1284.9165, 338.8102: 1282.3929, 393.477: 1279.6794, 404.3694: 1274.5383, 437.7567: 1272.3873, 482.9318: 1272.1067, 517.5897: 1270.0198, 541.1518: 1268.1338, 588.8421: 1268.1338, 588.8422: 1266.4405, 597.6003: 1266.4405}"/>
		<Output spanningTreeLength="1277.324" tourCost="2210.384" timeTaken="599.912" pruned="31" ellipsesRemaining="9" costOverTime="{26.1709: 2073.084, 44.7592: 2010.8533, 63.6393: 2001.3026, 72.9824: 2001.276, 82.6707: 1979.5188, 92.2086: 1978.8387, 92.2087: 1978.3927, 101.8474: 1978.3927, 101.8475: 1975.6227, 101.8476: 1967.2476, 101.848: 1967.0165, 111.6911: 1959.2956, 131.1221: 1958.4045, 150.644: 1958.4045, 150.6441: 1335.0766, 160.8148: 1335.0766, 160.8149: 1334.5991, 180.3899: 1328.3241, 190.4958: 1328.2952, 200.8271: 1318.0347, 252.1852: 1310.6066, 380.1715: 1310.6066, 380.1716: 1288.759, 447.7008: 1283.1975, 481.7734: 1277.3243, 599.9099: 1277.3243}"/>
		<Output spanningTreeLength="1258.974" tourCost="1932.606" timeTaken="596.161" pruned="31" ellipsesRemaining="9" costOverTime="{52.4186: 1612.8635, 61.8639: 1612.8635, 61.8718: 1600.973, 61.8719: 1597.9698, 71.4856: 1592.3678, 71.4859: 1591.1782, 80.8903: 1591.1782, 80.8904: 1588.0804, 99.9668: 1588.0804, 99.9669: 1527.4366, 109.5483: 1526.0374, 109.5484: 1521.0005, 120.3758: 1521.0005, 120.3759: 1446.1031, 120.3761: 1444.7806, 130.6956: 1419.6789, 130.6984: 1418.4893, 140.3205: 1403.2054, 150.0338: 1403.2054, 150.0339: 1386.5599, 209.3069: 1386.1374, 229.4388: 1383.1559, 249.7818: 1314.0549, 270.3061: 1305.3428, 280.9929: 1301.3971, 301.8586: 1301.0085, 366.4619: 1300.6361, 366.462: 1283.6875, 433.4319: 1283.6875, 433.432: 1281.8573, 433.4321: 1265.4585, 444.8714: 1261.1031, 456.0064: 1260.6011, 490.1961: 1260.5102, 524.9127: 1258.9991, 536.7229: 1258.9742, 596.1591: 1258.9742}"/>
		<Output spanningTreeLength="1289.608" tourCost="2201.688" timeTaken="596.273" pruned="31" ellipsesRemaining="9" costOverTime="{12.9881: 2295.4401, 22.1221: 2105.7266, 22.136: 2084.8945, 31.3573: 2084.8945, 31.3574: 2035.7223, 31.3605: 2035.7223, 31.3606: 2004.6372, 40.6041: 2004.6372, 40.6042: 2002.7853, 68.4573: 1969.1684, 87.1634: 1963.487, 96.5841: 1963.487, 96.5842: 1959.8583, 115.9137: 1959.8583, 115.9138: 1927.3806, 126.2167: 1922.8175, 146.0764: 1916.525, 165.8768: 1916.525, 165.8769: 1914.5184, 216.2346: 1914.5184, 216.2347: 1913.6927, 269.1101: 1913.6927, 269.1102: 1329.7344, 279.5288: 1327.1541, 289.9621: 1327.1541, 289.9622: 1320.6911, 300.406: 1315.7968, 310.8814: 1314.7944, 333.0733: 1314.7944, 333.0734: 1313.2398, 354.9815: 1306.472, 365.7931: 1306.472, 365.7932: 1303.6551, 398.8474: 1302.7207, 443.801: 1302.2955, 455.1071: 1300.7632, 512.8928: 1300.3856, 559.9033: 1293.2701, 583.8629: 1289.608, 596.2706: 1289.608}"/>
		<Output spanningTreeLength="1255.059" tourCost="1934.291" timeTaken="595.502" pruned="32" ellipsesRemaining="8" costOverTime="{52.491: 2351.7903, 62.0413: 2351.7903, 62.0553: 2122.6444, 62.0836: 2122.6444, 62.0837: 2099.4424, 71.5218: 2099.4424, 71.5219: 2087.0775, 71.5224: 2067.2221, 80.9013: 2067.2221, 80.9014: 2064.8491, 80.902: 2051.4786, 100.19: 2036.7757, 109.7267: 2036.1709, 119.6557: 2035.0951, 119.6563: 2008.9333, 149.2259: 2001.1619, 159.0361: 2001.1619, 159.0362: 1939.0549, 169.5203: 1937.1373, 179.507: 1930.3398, 229.756: 1930.3398, 229.7561: 1923.5402, 229.7566: 1914.6665, 239.9553: 1914.6665, 239.9554: 1913.4111, 260.4897: 1315.867, 270.8056: 1315.867, 270.8057: 1309.4448, 302.4472: 1305.5296, 312.9521: 1297.3782, 323.5143: 1297.3782, 323.5144: 1296.0303, 345.0158: 1277.8778, 366.6502: 1277.7879, 399.5723: 1272.4081, 421.5592: 1272.0115, 432.6839: 1268.7951, 432.684: 1263.7249, 512.4309: 1261.1704, 535.8: 1255.0592, 595.4988: 1255.0592}"/>
		<Output spanningTreeLength="1259.547" tourCost="2191.945" timeTaken="595.129" pruned="32" ellipsesRemaining="8" costOverTime="{12.8348: 2665.1714, 21.9935: 2331.1033, 22.002: 2325.6752, 31.3271: 2308.8191, 31.3273: 2295.8688, 31.3303: 2295.8688, 31.3304: 2231.9565, 40.558: 2231.9565, 40.5581: 2224.7778, 40.5585: 2203.4379, 49.9631: 2171.2858, 68.7524: 2156.2323, 68.7556: 2155.888, 78.0908: 2155.888, 78.0909: 2152.4598, 106.7687: 2146.016, 116.3603: 2146.016, 116.3604: 1974.1337, 145.6446: 1972.3169, 165.4704: 1972.3169, 165.4705: 1956.1252, 175.3576: 1956.1252, 175.3577: 1919.8567, 175.3578: 1919.0267, 175.3582: 1716.2025, 225.8294: 1716.2025, 225.8295: 1715.3689, 236.8066: 1715.3689, 236.8067: 1713.8281, 247.0637: 1713.0829, 331.7614: 1713.0829, 331.7615: 1265.5391, 397.4481: 1264.6954, 453.551: 1263.2539, 499.7599: 1263.2539, 499.76: 1263.2258, 559.232: 1263.0323, 571.1203: 1259.5473, 595.1268: 1259.5473}"/>
		<Output spanningTreeLength="1290.952" tourCost="2230.331" timeTaken="598.663" pruned="31" ellipsesRemaining="9" costOverTime="{25.9302: 2577.4703, 35.1548: 2577.4703, 35.1631: 2497.4074, 35.1695: 2482.7761, 44.6064: 2482.7761, 44.6065: 2466.6748, 53.8628: 2461.7162, 53.8634: 2461.7162, 53.8635: 2442.819, 63.2286: 2442.819, 63.2287: 2106.453, 63.2402: 2054.4508, 72.6036: 2054.4508, 72.6037: 2045.5309, 72.6042: 2025.5309, 82.1173: 1970.503, 82.1179: 1957.9044, 130.3579: 1957.9044, 130.358: 1953.8353, 130.3586: 1952.3337, 140.0604: 1951.6763, 140.061: 1940.9472, 149.8016: 1939.7615, 149.8021: 1938.6048, 179.3614: 1937.7937, 189.5146: 1937.7937, 189.5147: 1935.8466, 199.5269: 1818.727, 229.7581: 1322.1612, 240.1359: 1320.5876, 240.136: 1320.4041, 260.8086: 1320.2905, 292.2769: 1308.7389, 302.9334: 1308.7389, 302.9335: 1308.5774, 313.5267: 1308.1226, 345.9293: 1308.1226, 345.9294: 1304.9077, 378.68: 1298.0019, 390.6944: 1296.791, 469.1688: 1293.7534, 492.1943: 1292.1987, 515.4859: 1292.1987, 515.486: 1291.2304, 550.8671: 1290.9525, 598.6602: 1290.9525}"/>
		<Output spanningTreeLength="1265.119" tourCost="2166.768" timeTaken="597.861" pruned="31" ellipsesRemaining="9" costOverTime="{53.0851: 1559.6177, 53.0852: 1547.3061, 62.5364: 1547.3061, 62.5443: 1474.1639, 71.9191: 1424.0008, 71.9192: 1417.3691, 81.4007: 1417.3691, 81.4008: 1410.133, 90.9448: 1410.133, 90.9449: 1404.609, 100.593: 1393.9547, 120.1774: 1393.9547, 120.1775: 1322.9743, 120.1776: 1318.9909, 129.8053: 1303.0933, 129.8054: 1302.8437, 139.4372: 1300.4418, 159.4222: 1299.7477, 189.102: 1293.8758, 199.0485: 1293.8758, 199.0486: 1292.2859, 259.8472: 1290.4836, 270.1162: 1289.2644, 270.1163: 1288.1034, 280.9696: 1287.3282, 291.381: 1287.0262, 322.9953: 1286.828, 388.5862: 1286.7352, 399.5684: 1284.0356, 433.0679: 1283.7776, 444.3353: 1283.7776, 444.3354: 1273.2348, 455.6861: 1273.2348, 455.6862: 1272.5103, 466.9937: 1272.1756, 513.4164: 1271.3164, 549.5126: 1265.1189, 597.8587: 1265.1189}"/>
		<Output spanningTreeLength="1251.1" tourCost="2170.162" timeTaken="602.185" pruned="32" ellipsesRemaining="8" costOverTime="{12.8973: 2287.1734, 12.8974: 2208.2199, 22.0323: 2206.0452, 31.2716: 2206.0452, 31.2717: 2173.2653, 31.2724: 2115.7255, 40.4969: 2114.5163, 40.4971: 2113.7115, 49.8778: 2103.7594, 59.3597: 2103.5283, 78.3204: 2103.5283, 78.3205: 1993.3101, 78.3238: 1991.4441, 87.7028: 1991.4441, 87.7029: 1951.952, 87.703: 1917.7367, 97.2353: 1916.1568, 135.473: 1915.2545, 145.334: 1914.8093, 155.0856: 1914.8093, 155.0857: 1386.9185, 164.9087: 1386.9185, 164.9088: 1386.0116, 174.7301: 1382.8248, 184.934: 1382.8248, 184.9341: 1371.722, 194.8882: 1371.722, 194.8883: 1368.992, 204.8938: 1360.8395, 204.8939: 1266.4444, 307.7567: 1266.4444, 307.7568: 1260.8476, 339.6017: 1258.4566, 404.9201: 1256.2427, 438.4147: 1251.4335, 542.4438: 1251.1005, 599.0797: 1251.1005}"/>
		<Output spanningTreeLength="1277.471" tourCost="2179.809" timeTaken="599.388" pruned="31" ellipsesRemaining="9" costOverTime="{26.1704: 2605.6975, 26.1705: 2326.2208, 35.3431: 2326.2208, 35.3432: 2322.9592, 44.5539: 2322.9592, 44.554: 2301.2068, 53.7915: 2301.2068, 53.7916: 1984.4836, 72.6446: 1984.4836, 72.6447: 1964.2133, 82.2069: 1962.3094, 91.6407: 1955.8443, 150.2582: 1917.4629, 180.294: 1917.4629, 180.2941: 1902.0657, 190.2323: 1899.6434, 220.417: 1325.2201, 240.9653: 1324.9595, 240.9654: 1318.9909, 261.8239: 1305.5456, 261.824: 1293.8115, 346.3808: 1292.4651, 368.2261: 1290.8219, 412.2651: 1290.8219, 412.2652: 1288.1492, 434.9405: 1281.7201, 599.3855: 1277.4712, 599.3858: 1277.4712}"/>
		<Output spanningTreeLength="1267.884" tourCost="2167.16" timeTaken="600.074" pruned="31" ellipsesRemaining="9" costOverTime="{26.0057: 2396.9488, 35.2493: 2396.9488, 35.2577: 2272.5247, 44.5192: 2272.5247, 44.5193: 2134.1911, 44.5225: 2134.1911, 44.5226: 2051.7536, 53.8001: 2051.7536, 53.8002: 2050.9042, 72.4701: 2016.6637, 72.4702: 2016.4635, 101.2687: 1361.1322, 110.8541: 1358.279, 110.8542: 1358.279, 110.8543: 1357.2431, 120.4271: 1357.2431, 120.4272: 1333.6943, 139.7678: 1330.7039, 139.7679: 1327.5674, 179.0206: 1327.093, 198.9928: 1327.093, 198.9929: 1320.4951, 219.1346: 1317.6672, 249.8135: 1296.5435, 260.0839: 1291.788, 280.983: 1290.1721, 302.503: 1290.1721, 302.5031: 1287.513, 334.5142: 1287.4031, 334.5144: 1287.1319, 356.2447: 1286.0529, 367.1102: 1283.7091, 411.3907: 1283.7091, 411.3908: 1283.4621, 422.7448: 1282.4099, 446.0309: 1277.655, 480.2773: 1269.5402, 515.4211: 1269.5402, 515.4212: 1269.3637, 588.0493: 1267.8845, 596.8098: 1267.8845}"/>
		<Output spanningTreeLength="1264.676" tourCost="2199.759" timeTaken="594.609" pruned="32" ellipsesRemaining="8" costOverTime="{12.982: 2462.6718, 22.1694: 2368.8608, 22.1695: 2368.6598, 22.18: 2337.6509, 31.5885: 2337.556, 31.5886: 2335.7704, 31.5891: 2319.8381, 40.9533: 2319.8381, 40.9534: 2307.8827, 40.9535: 2299.276, 40.9539: 2236.4286, 50.3569: 2199.4054, 59.6582: 2199.4054, 59.6583: 2088.6643, 59.6614: 2088.6643, 59.6615: 2051.1296, 69.2018: 2016.0299, 78.5567: 2016.0299, 78.5568: 1945.4234, 107.1415: 1944.6502, 107.1416: 1944.6502, 107.1417: 1937.5523, 156.1844: 1937.4128, 156.1847: 1878.1877, 176.4542: 1360.4686, 186.361: 1350.8569, 186.3611: 1326.3535, 196.7346: 1302.8443, 217.3726: 1302.5052, 227.562: 1298.1534, 237.7068: 1297.7774, 237.7069: 1296.3573, 278.9352: 1283.2321, 289.6021: 1278.9084, 353.5001: 1275.128, 364.5307: 1275.128, 364.5308: 1274.4324, 431.2128: 1274.4324, 431.2129: 1272.7756, 570.6262: 1264.6759, 594.6067: 1264.6759}"/>
		<Output spanningTreeLength="1248.47" tourCost="2168.199" timeTaken="603.118" pruned="32" ellipsesRemaining="8" costOverTime="{39.2044: 2055.3917, 48.4729: 2055.3917, 48.4809: 2032.3881, 67.1161: 2023.8865, 67.1192: 2022.6944, 76.5046: 2019.8117, 76.5051: 2019.0882, 85.9057: 2016.6908, 124.7025: 2014.913, 144.1516: 1366.6899, 153.9869: 1366.6899, 153.987: 1354.5106, 164.3659: 1354.1488, 194.0401: 1351.8542, 214.284: 1351.8542, 214.2841: 1309.3643, 224.3907: 1302.0153, 234.5644: 1302.0153, 234.5645: 1299.5822, 244.7668: 1299.5822, 244.7669: 1297.3111, 254.9865: 1292.136, 265.3204: 1291.5107, 275.8032: 1284.1082, 328.6007: 1256.1896, 393.8398: 1255.9081, 438.6109: 1255.9081, 438.611: 1255.4252, 484.6401: 1248.4705, 599.9912: 1248.4705}"/>
		<Output spanningTreeLength="1276.284" tourCost="2214.027" timeTaken="602.408" pruned="32" ellipsesRemaining="8" costOverTime="{13.014: 2618.624, 22.0657: 2618.624, 22.074: 2245.3308, 22.0891: 2242.6587, 31.3732: 2220.8593, 40.576: 2220.8593, 40.5761: 2215.9385, 40.5762: 2214.0897, 40.5767: 2200.0603, 59.158: 2158.6889, 106.1749: 2158.6889, 106.175: 1962.6051, 106.1751: 1953.2663, 106.1782: 1946.4607, 144.9588: 1939.9417, 144.9593: 1939.9417, 144.9594: 1939.8189, 154.7292: 1938.1005, 184.3977: 1937.8257, 194.2824: 1937.8257, 194.2825: 1936.0322, 194.2826: 1304.2566, 204.2992: 1304.2566, 204.2993: 1287.3208, 317.7039: 1287.3208, 317.704: 1282.293, 349.9701: 1282.293, 349.9702: 1281.7208, 382.4934: 1281.263, 393.4903: 1281.263, 393.4904: 1280.826, 530.3749: 1280.826, 530.375: 1278.2763, 553.9895: 1276.7554, 566.0015: 1276.2843, 599.1032: 1276.2843}"/>
		<Output spanningTreeLength="1253.875" tourCost="1931.283" timeTaken="593.5" pruned="31" ellipsesRemaining="9" costOverTime="{12.9424: 1518.755, 12.9456: 1515.1873, 22.2076: 1515.1873, 22.2157: 1462.6473, 31.3507: 1399.9998, 40.5256: 1399.9998, 40.5257: 1335.4804, 49.7563: 1330.5355, 59.0557: 1330.5355, 59.0558: 1319.6422, 77.7293: 1319.6422, 77.7294: 1318.8691, 87.1204: 1318.8691, 87.1205: 1315.0109, 106.1809: 1310.1575, 115.6703: 1285.2374, 154.2963: 1285.2374, 154.2964: 1275.895, 174.047: 1275.895, 174.0471: 1273.2473, 328.9298: 1259.1826, 383.5985: 1259.1826, 383.5986: 1257.489, 462.5428: 1254.2435, 474.0558: 1253.9522, 497.6337: 1253.8745, 593.4979: 1253.8745}"/>
		<Output spanningTreeLength="1270.737" tourCost="2169.06" timeTaken="599.534" pruned="32" ellipsesRemaining="8" costOverTime="{13.1179: 2050.6023, 22.2326: 2047.0628, 22.2506: 2046.5894, 31.4212: 2046.455, 40.8818: 2046.455, 40.8819: 2046.2515, 40.8824: 2046.2515, 40.8825: 2040.5242, 50.2766: 2032.036, 50.2767: 2032.036, 50.2768: 2027.0556, 59.5146: 2027.0556, 59.5147: 2026.891, 59.5148: 2021.2719, 59.5152: 2018.3843, 69.0909: 2018.3843, 69.091: 2008.6577, 78.7496: 2008.6577, 78.7497: 1989.2541, 98.0849: 1985.6842, 107.5575: 1985.6842, 107.5576: 1335.0097, 117.2364: 1335.0097, 117.2365: 1332.0945, 127.1916: 1332.0945, 127.1917: 1319.9834, 156.7437: 1318.4848, 227.499: 1318.4848, 227.4991: 1315.5466, 237.6627: 1308.2293, 248.2226: 1299.1096, 269.0436: 1299.1096, 269.0437: 1294.8184, 279.6562: 1294.8184, 279.6563: 1292.0726, 322.0838: 1287.6375, 376.4454: 1281.4418, 432.7853: 1272.3215, 432.7854: 1271.0453, 514.4161: 1270.7366, 599.529: 1270.7366}"/>
		<Output spanningTreeLength="1280.277" tourCost="2222.846" timeTaken="600.181" pruned="31" ellipsesRemaining="9" costOverTime="{25.8839: 2092.8265, 35.2179: 2092.8265, 35.218: 2087.5512, 44.5956: 2079.3022, 53.9944: 2018.9091, 63.366: 1998.6861, 63.3661: 1438.0777, 82.3765: 1438.0777, 82.3766: 1437.7657, 91.7591: 1437.1263, 101.205: 1415.8055, 101.2051: 1405.6609, 120.269: 1405.6609, 120.2691: 1387.0572, 129.841: 1377.3048, 139.438: 1376.9557, 139.4381: 1337.633, 158.9271: 1337.633, 158.9272: 1330.213, 168.7088: 1327.1887, 188.497: 1325.9361, 198.3725: 1325.9361, 198.3726: 1313.8637, 228.328: 1313.8637, 228.3281: 1305.6092, 258.9639: 1302.7964, 333.6832: 1302.7964, 333.6833: 1286.909, 344.5837: 1286.909, 344.5838: 1282.9458, 355.2658: 1280.622, 421.8309: 1280.622, 421.831: 1280.4451, 539.3755: 1280.277, 597.1113: 1280.277}"/>
		<Output spanningTreeLength="1268.834" tourCost="2168.155" timeTaken="597.658" pruned="31" ellipsesRemaining="9" costOverTime="{12.9421: 2488.6083, 22.0115: 2488.6083, 22.0223: 2332.8897, 22.0224: 2328.0558, 22.0341: 2327.0645, 31.1941: 2319.1948, 40.4012: 2319.1948, 40.4013: 2315.6184, 40.4014: 2314.1604, 40.4019: 2308.568, 49.8993: 2308.568, 49.8994: 2304.7807, 49.9001: 2271.1704, 59.4221: 2271.1704, 59.4222: 2128.6328, 68.7143: 2128.2384, 68.7147: 2123.2698, 78.361: 2073.7699, 78.3611: 2073.7699, 78.3612: 2071.401, 78.3615: 2071.401, 78.3616: 2061.5971, 87.9009: 2004.9937, 97.6218: 2003.4482, 97.6222: 1962.2361, 107.1439: 1956.927, 126.8961: 1938.1708, 136.6309: 1935.6137, 146.307: 1935.2445, 166.2578: 1921.7265, 186.1309: 1330.8608, 196.1035: 1330.406, 206.1458: 1321.6965, 206.1459: 1310.6698, 226.3302: 1310.6698, 226.3303: 1310.5094, 288.911: 1309.933, 299.4333: 1306.7774, 320.9481: 1304.8912, 342.923: 1297.1322, 342.9231: 1294.7805, 364.8053: 1292.3022, 375.8876: 1291.6716, 398.2692: 1277.1519, 420.8515: 1273.7045, 466.9201: 1273.6852, 490.2279: 1273.6852, 490.228: 1270.8616, 490.2281: 1270.6489, 502.1229: 1270.6489, 502.123: 1270.1493, 513.9804: 1270.0344, 597.6543: 1268.8341, 597.6545: 1268.8341}"/>
		<Output spanningTreeLength="1271.022" tourCost="2176.431" timeTaken="600.343" pruned="32" ellipsesRemaining="8" costOverTime="{39.1454: 2103.9667, 48.6066: 2102.6606, 57.9015: 2102.6606, 57.9016: 2034.5622, 67.2203: 2034.0895, 67.2204: 2029.2123, 76.931: 2029.2123, 76.9311: 2028.0409, 76.9318: 2019.1381, 86.322: 2013.3795, 86.3221: 2011.3106, 95.7981: 1988.4548, 105.7624: 1980.6191, 164.5402: 1957.4705, 184.4498: 1936.0011, 215.2261: 1925.6908, 226.4185: 1925.6908, 226.4186: 1925.4221, 269.5792: 1925.3424, 301.1518: 1920.0387, 311.99: 1908.562, 322.6342: 1908.562, 322.6343: 1908.3159, 322.6347: 1904.1525, 334.3819: 1311.799, 346.1419: 1311.799, 346.142: 1311.7715, 367.9913: 1306.6016, 379.0092: 1306.445, 412.5034: 1306.445, 412.5035: 1304.0258, 457.4507: 1302.3281, 457.4508: 1297.7771, 468.9305: 1297.7027, 480.6469: 1297.1462, 504.949: 1295.8774, 504.9491: 1275.9814, 564.26: 1271.022, 597.1793: 1271.022}"/>
		<Output spanningTreeLength="1273.912" tourCost="2215.709" timeTaken="603.008" pruned="31" ellipsesRemaining="9" costOverTime="{65.7078: 1417.5222, 65.7104: 1414.1451, 75.3739: 1414.1451, 75.382: 1379.0137, 84.9147: 1379.0137, 84.9148: 1375.9649, 94.6458: 1340.3791, 104.1755: 1340.3791, 104.1756: 1339.2038, 113.7348: 1338.6625, 113.7349: 1338.4686, 123.385: 1338.4686, 123.3851: 1337.2287, 123.3852: 1337.0953, 132.9936: 1336.7184, 132.9937: 1336.265, 142.7233: 1336.265, 142.7234: 1334.9852, 153.5863: 1329.0603, 153.5864: 1327.6645, 163.3827: 1326.7065, 173.2089: 1326.7065, 173.209: 1325.5362, 183.5218: 1324.6094, 203.4273: 1323.4268, 265.0618: 1323.4268, 265.0619: 1318.1383, 297.4784: 1308.3394, 308.1448: 1308.3394, 308.1449: 1307.6991, 318.7224: 1303.7489, 350.8072: 1299.4449, 361.6058: 1296.6063, 383.551: 1296.0185, 394.537: 1296.0185, 394.5371: 1293.6245, 473.6902: 1292.1413, 485.0597: 1277.0976, 531.7349: 1273.9123, 599.9809: 1273.9123}"/>
		<Output spanningTreeLength="1261.967" tourCost="2188.309" timeTaken="592.701" pruned="32" ellipsesRemaining="8" costOverTime="{12.8886: 1528.9879, 12.891: 1501.8142, 22.0693: 1473.885, 31.2161: 1473.885, 31.2162: 1376.0703, 40.5896: 1376.0703, 40.5898: 1355.9625, 49.9274: 1355.9625, 49.9275: 1346.619, 59.1857: 1346.619, 59.1858: 1324.6996, 77.807: 1324.6996, 77.8071: 1322.9585, 87.3657: 1322.9585, 87.3658: 1322.4424, 135.5928: 1322.4424, 135.5929: 1319.6634, 145.2511: 1315.5911, 164.7922: 1306.5518, 164.7923: 1304.8126, 184.7458: 1302.3552, 204.6664: 1295.6259, 318.6973: 1276.5704, 340.1168: 1262.0002, 509.2801: 1262.0002, 509.2802: 1261.9674, 592.6984: 1261.9674}"/>
		<Output spanningTreeLength="1275.133" tourCost="2221.503" timeTaken="602.266" pruned="32" ellipsesRemaining="8" costOverTime="{39.4265: 2047.7334, 48.7892: 2047.7334, 48.7977: 2010.0559, 77.1083: 2005.7088, 96.309: 2004.2045, 125.4342: 2004.1992, 144.8296: 2004.1992, 144.8297: 1993.1525, 154.566: 1345.5276, 164.4488: 1345.5276, 164.4489: 1337.3692, 234.4178: 1328.8922, 244.6253: 1328.8922, 244.6254: 1306.5426, 254.8717: 1306.5426, 254.8718: 1283.2382, 286.0384: 1283.2382, 286.0385: 1282.0143, 449.3237: 1282.0143, 449.3238: 1280.1354, 483.8537: 1279.0898, 554.5334: 1275.1332, 599.1397: 1275.1332}"/>
		<Output spanningTreeLength="1294.976" tourCost="2199.51" timeTaken="601.691" pruned="30" ellipsesRemaining="10" costOverTime="{25.9094: 2146.1038, 35.0951: 2146.1038, 35.0952: 2145.7409, 44.3199: 2139.8558, 44.3205: 2005.8765, 53.6329: 1995.1154, 53.6361: 1994.9643, 63.1346: 1994.9643, 63.1347: 1993.7145, 63.1348: 1992.9271, 82.2047: 1989.3128, 92.1565: 1989.0466, 101.7556: 1986.8334, 101.7561: 1977.1029, 111.3576: 1974.3423, 111.358: 1974.3423, 111.3581: 1964.8589, 120.9471: 1961.9439, 120.9472: 1961.3993, 131.0244: 1961.3993, 131.0245: 1959.6643, 140.7077: 1959.6643, 140.7078: 1959.6637, 140.7084: 1946.6954, 150.42: 1943.0396, 170.3187: 1943.0396, 170.3188: 1939.0954, 170.3193: 1936.9968, 180.5341: 1932.7854, 190.5031: 1932.7854, 190.5032: 1927.7956, 211.2734: 1841.824, 231.684: 1841.824, 231.6841: 1828.3613, 262.6885: 1820.1628, 283.5745: 1809.1805, 294.1461: 1808.3875, 294.1462: 1802.6391, 304.6838: 1802.0318, 347.5963: 1798.4181, 369.4962: 1795.4425, 403.0795: 1791.0823, 425.6122: 1788.0952, 448.3024: 1306.8493, 459.6877: 1305.8181, 471.1633: 1305.8181, 471.1634: 1305.1806, 482.6592: 1305.1806, 482.6593: 1303.3639, 553.7307: 1302.64, 565.6546: 1296.9664, 577.648: 1296.9664, 577.6481: 1294.9761, 598.5443: 1294.9761}"/>
		<Output spanningTreeLength="1262.567" tourCost="1948.396" timeTaken="597.244" pruned="32" ellipsesRemaining="8" costOverTime="{26.0438: 1438.3205, 26.0439: 1438.3205, 26.0463: 1432.4895, 35.3565: 1432.4895, 35.3644: 1427.6649, 53.9613: 1411.9148, 63.3032: 1401.6135, 72.7291: 1379.95, 101.1253: 1352.8091, 110.7111: 1339.2696, 120.5864: 1339.1341, 120.5865: 1334.5287, 139.878: 1320.3785, 179.1473: 1319.5705, 189.1204: 1310.4193, 249.8779: 1306.0462, 260.2205: 1306.0462, 260.2206: 1305.5939, 291.4306: 1305.1965, 302.1418: 1302.2319, 323.2801: 1302.2319, 323.2802: 1299.3912, 388.4532: 1288.7963, 399.4671: 1288.7963, 399.4672: 1285.2863, 549.2307: 1285.2863, 549.2308: 1282.966, 549.2309: 1270.9459, 597.2389: 1262.5666, 597.2415: 1262.5666}"/>
		<Output spanningTreeLength="1300.58" tourCost="2239.653" timeTaken="591.269" pruned="30" ellipsesRemaining="10" costOverTime="{26.031: 2317.2251, 44.506: 2034.2744, 53.783: 2034.2744, 53.7831: 1997.4398, 53.7836: 1945.2897, 63.1303: 1944.5884, 72.4858: 1939.2899, 72.4864: 1932.9351, 101.1157: 1932.8672, 140.4281: 1932.8672, 140.4282: 1923.6075, 169.9959: 1921.4854, 189.9125: 1917.6123, 230.4699: 1916.499, 230.4703: 1916.499, 230.4704: 1906.1006, 304.3844: 1904.0349, 315.1637: 1903.7214, 325.939: 1899.7442, 325.9391: 1789.4769, 347.5026: 1353.227, 369.3059: 1329.1797, 369.306: 1326.338, 380.3354: 1320.2709, 391.3899: 1317.991, 436.4618: 1305.6341, 449.1783: 1304.0622, 507.3583: 1304.0622, 507.3584: 1300.5796, 591.2664: 1300.5796}"/>
		<Output spanningTreeLength="1275.294" tourCost="2177.428" timeTaken="602.785" pruned="31" ellipsesRemaining="9" costOverTime="{25.9406: 1520.294, 25.9407: 1520.294, 25.9432: 1504.2509, 35.2492: 1500.393, 35.2493: 1498.2312, 44.5625: 1498.2312, 44.5626: 1465.3597, 44.5627: 1464.621, 53.9697: 1464.621, 53.9698: 1431.8858, 53.9699: 1401.7714, 63.3944: 1388.2368, 72.7736: 1388.2368, 72.7737: 1375.5867, 82.1565: 1375.5867, 82.1566: 1370.3136, 91.5516: 1366.2187, 91.5517: 1365.2624, 101.0577: 1354.9019, 110.5387: 1351.4754, 139.7426: 1335.3423, 149.6771: 1335.3389, 159.8229: 1335.0662, 169.601: 1335.0662, 169.6011: 1309.5002, 189.3593: 1309.5002, 189.3594: 1308.1249, 219.3746: 1308.1249, 219.3747: 1302.0899, 239.9398: 1302.0822, 250.1752: 1302.0822, 250.1753: 1291.9096, 260.764: 1291.9096, 260.7641: 1291.8028, 271.101: 1289.7092, 346.5355: 1289.7092, 346.5356: 1286.8419, 481.1765: 1285.2576, 504.5477: 1280.9674, 541.0484: 1280.9674, 541.0485: 1275.2939, 599.6876: 1275.2939}"/>
		<Output spanningTreeLength="1265.541" tourCost="2169.471" timeTaken="594.347" pruned="32" ellipsesRemaining="8" costOverTime="{12.8387: 2238.9541, 12.8388: 2235.2191, 21.9372: 2235.2191, 21.9454: 2218.2129, 21.9615: 2209.4213, 31.2683: 2209.1862, 31.2688: 2209.1862, 31.2689: 2007.0676, 40.5525: 2005.3404, 40.5526: 2001.4297, 49.7685: 2001.4297, 49.7686: 1960.6201, 59.1236: 1960.462, 59.124: 1946.6728, 68.5881: 1946.6728, 68.5882: 1939.5805, 77.9433: 1939.5805, 77.9434: 1938.4507, 106.2916: 1930.1319, 174.3332: 1924.2748, 204.302: 1924.2748, 204.3021: 1923.638, 214.399: 1923.638, 214.3991: 1921.8797, 214.3997: 1913.6189, 234.7993: 1913.6189, 234.7994: 1909.3686, 234.7999: 1909.3686, 234.8: 1783.7294, 255.8595: 1783.0749, 319.6415: 1782.8875, 341.8375: 1318.158, 352.6965: 1316.6827, 418.9775: 1316.6827, 418.9776: 1314.0709, 418.9777: 1311.0228, 441.4902: 1311.0228, 441.4903: 1300.7829, 452.9246: 1273.4049, 475.8078: 1268.7394, 522.528: 1268.7394, 522.5281: 1267.6386, 534.2073: 1267.6386, 534.2074: 1265.5415, 594.3428: 1265.5415}"/>
		<Output spanningTreeLength="1307.504" tourCost="2213.568" timeTaken="594.532" pruned="29" ellipsesRemaining="11" costOverTime="{39.1233: 2074.001, 48.4092: 2074.001, 48.4176: 2051.1904, 48.4177: 2040.6742, 48.4317: 2033.1013, 57.7196: 2000.3203, 57.7202: 1988.4888, 67.0849: 1985.8474, 67.0854: 1984.6825, 76.5267: 1966.9798, 76.5273: 1964.7897, 95.4172: 1964.7897, 95.4173: 1959.4046, 114.6817: 1959.4046, 114.6818: 1950.8225, 114.6823: 1947.9583, 124.3499: 1945.2471, 163.5217: 1944.0257, 193.3824: 1943.5372, 275.4483: 1943.1857, 318.5615: 1943.0311, 351.1202: 1940.9405, 351.1208: 1939.0785, 463.4288: 1939.0785, 463.4289: 1919.9046, 486.6937: 1328.5754, 510.3058: 1327.965, 522.1552: 1323.8825, 557.9952: 1318.5278, 557.9953: 1307.5429, 594.5297: 1307.5039, 594.5299: 1307.5039}"/>
		<Output spanningTreeLength="1269.681" tourCost="2169.555" timeTaken="594.084" pruned="31" ellipsesRemaining="9" costOverTime="{12.9231: 2123.996, 22.1037: 2123.6954, 31.2702: 2087.7984, 31.2707: 2047.6532, 40.6845: 2038.762, 40.6851: 2030.8826, 49.9455: 2030.8826, 49.9456: 2030.0012, 49.9461: 2012.2771, 59.3766: 2008.063, 59.3771: 1968.3857, 68.7059: 1967.4664, 87.7861: 1950.8225, 97.3032: 1948.0286, 97.3036: 1945.1629, 135.8071: 1369.309, 165.2212: 1364.4153, 175.5064: 1362.2654, 185.4601: 1350.0422, 205.4621: 1298.5711, 205.4622: 1283.3949, 277.5993: 1278.6714, 277.5994: 1274.7362, 309.4426: 1274.7362, 309.4427: 1274.1902, 352.4731: 1273.0389, 363.4216: 1270.1716, 594.081: 1269.6813, 594.0812: 1269.6813}"/>
		<Output spanningTreeLength="1277.964" tourCost="1978.864" timeTaken="600.014" pruned="32" ellipsesRemaining="8" costOverTime="{26.3814: 2408.5653, 35.681: 2408.5653, 35.6891: 2300.6763, 35.6892: 2244.7094, 44.9176: 2244.7094, 44.9177: 2087.0788, 54.1416: 2087.0788, 54.1417: 2029.8771, 63.5954: 2000.5645, 72.9783: 1999.2752, 82.5944: 1998.2685, 101.774: 1994.8946, 101.7745: 1988.2642, 111.3208: 1983.4132, 111.3241: 1957.4553, 130.6202: 1358.2232, 170.3044: 1358.2232, 170.3045: 1350.5942, 190.6126: 1350.5942, 190.6127: 1349.8559, 201.1388: 1349.3637, 211.2092: 1345.7919, 221.4719: 1337.0449, 231.5421: 1337.0449, 231.5422: 1335.5168, 241.7727: 1329.34, 252.065: 1329.34, 252.0651: 1313.5428, 272.7461: 1304.0449, 413.8128: 1293.5013, 424.9073: 1291.8472, 436.2559: 1291.8472, 436.256: 1290.6498, 493.2732: 1290.6498, 493.2733: 1288.3291, 516.7126: 1282.5022, 540.0785: 1280.0764, 563.7606: 1279.3669, 576.0319: 1277.9642, 599.9938: 1277.9642}"/>
		<Output spanningTreeLength="1260.393" tourCost="2187.455" timeTaken="593.326" pruned="31" ellipsesRemaining="9" costOverTime="{12.9859: 2342.9553, 12.986: 2177.1234, 22.1339: 2177.1234, 22.1421: 2145.8478, 22.1423: 2145.8478, 22.1452: 2143.9629, 22.1571: 2137.4764, 50.051: 2125.338, 59.324: 2125.338, 59.3241: 2113.4272, 68.6551: 2105.0257, 68.6557: 2100.7889, 78.0785: 2099.4306, 78.079: 1992.634, 87.5155: 1990.9991, 87.5156: 1987.2573, 87.5188: 1984.7948, 96.987: 1984.7948, 96.9871: 1984.5764, 106.5159: 1387.3109, 116.1384: 1379.9491, 125.7416: 1378.8808, 135.4519: 1365.8415, 145.1491: 1357.7026, 145.1492: 1354.2259, 164.7376: 1348.617, 174.7061: 1348.2248, 195.0883: 1344.499, 205.1148: 1341.6783, 215.1979: 1318.4896, 225.3534: 1315.9181, 235.5334: 1315.2497, 308.4314: 1312.7956, 319.0184: 1299.8458, 362.3581: 1298.4321, 384.2329: 1272.9329, 395.3044: 1272.2734, 406.5359: 1271.3809, 451.6186: 1269.5599, 474.6006: 1263.4826, 569.1275: 1263.4826, 569.1276: 1260.3927, 593.3232: 1260.3927}"/>
		<Output spanningTreeLength="1262.868" tourCost="2188.037" timeTaken="598.17" pruned="32" ellipsesRemaining="8" costOverTime="{26.1685: 2269.1805, 35.423: 2269.1805, 35.4311: 2149.3849, 35.4444: 2053.4088, 44.687: 2053.4088, 44.6871: 1430.9523, 53.9971: 1411.3781, 53.9972: 1404.7188, 63.2703: 1401.4137, 63.2704: 1398.2163, 72.5874: 1398.1807, 81.984: 1398.1807, 81.9841: 1396.5412, 91.4285: 1380.6405, 100.9448: 1380.6405, 100.9449: 1376.7169, 110.5167: 1374.3827, 120.321: 1371.9613, 129.9295: 1334.0827, 129.9296: 1334.0827, 129.9297: 1333.7865, 139.865: 1329.7277, 159.6572: 1321.6969, 209.362: 1310.5729, 229.7429: 1310.5729, 229.743: 1309.9575, 229.7431: 1308.1343, 291.8996: 1304.6888, 312.9999: 1304.6888, 313.0: 1303.5056, 334.388: 1303.5056, 334.3881: 1301.6285, 345.1296: 1300.7642, 355.9807: 1300.7642, 355.9808: 1299.711, 388.716: 1299.415, 422.3086: 1298.1551, 445.0113: 1290.9063, 490.8349: 1290.0633, 502.4518: 1271.1467, 537.9468: 1262.8678, 598.1675: 1262.8678}"/>
		<Output spanningTreeLength="1285.935" tourCost="2200.812" timeTaken="592.942" pruned="32" ellipsesRemaining="8" costOverTime="{39.036: 2166.6636, 48.3326: 2166.6636, 48.3407: 2139.8059, 48.3408: 1444.8771, 57.6903: 1417.8469, 67.0135: 1417.8469, 67.0136: 1417.3369, 67.0137: 1417.1852, 76.3731: 1417.1852, 76.3732: 1397.293, 85.8138: 1386.547, 124.2734: 1383.9513, 134.0329: 1383.7759, 143.7119: 1383.7759, 143.712: 1379.6335, 153.4913: 1379.6335, 153.4914: 1371.4359, 173.144: 1371.3147, 183.0914: 1367.9602, 183.0915: 1362.9519, 203.4525: 1355.1586, 213.7561: 1339.9151, 234.0771: 1339.9151, 234.0772: 1332.1968, 244.7367: 1329.0095, 265.3834: 1329.0095, 265.3835: 1313.8314, 307.4336: 1313.8314, 307.434: 1304.3756, 394.5221: 1302.4171, 428.0364: 1302.4171, 428.0365: 1299.7731, 439.6579: 1293.3452, 462.3913: 1292.235, 520.3732: 1290.7882, 568.625: 1287.5775, 592.939: 1285.9352, 592.9392: 1285.9352}"/>
		<Output spanningTreeLength="1268.415" tourCost="2167.526" timeTaken="598.494" pruned="32" ellipsesRemaining="8" costOverTime="{13.0845: 2223.1531, 22.3635: 2151.2443, 22.3771: 2151.2443, 22.3772: 2138.6055, 31.6723: 2121.7742, 40.8846: 2120.4783, 50.1315: 2120.4783, 50.1316: 2060.5875, 50.1347: 2049.1943, 59.4022: 2048.3097, 59.4027: 2047.3256, 68.7689: 2037.2197, 88.1323: 2033.8281, 97.5913: 2033.8281, 97.5914: 2032.5871, 97.592: 2016.6911, 107.4057: 2015.8041, 126.8355: 2009.5071, 136.5633: 2009.5071, 136.5634: 2002.3763, 146.9449: 1995.2608, 146.9455: 1991.2684, 156.7428: 1991.2684, 156.7429: 1989.007, 176.9535: 1989.007, 176.9536: 1949.5017, 196.856: 1938.1532, 217.1495: 1370.1829, 227.9168: 1321.4306, 238.0879: 1315.7254, 248.3642: 1314.9643, 258.7843: 1313.3046, 269.175: 1313.0213, 290.8108: 1313.0213, 290.8109: 1307.2695, 312.9468: 1303.591, 323.6092: 1297.598, 400.7554: 1297.598, 400.7555: 1291.5546, 411.8641: 1287.8523, 480.2261: 1287.8523, 480.2262: 1287.5836, 515.1543: 1283.9526, 515.1544: 1277.0557, 526.875: 1274.2205, 550.4299: 1273.147, 586.3903: 1268.4151, 598.4912: 1268.4151}"/>
		<Output spanningTreeLength="1299.774" tourCost="2221.043" timeTaken="592.485" pruned="31" ellipsesRemaining="9" costOverTime="{25.9886: 2655.9969, 25.9887: 2613.8967, 35.241: 2613.8967, 35.2411: 2315.045, 35.2467: 2315.045, 35.2468: 2296.8501, 44.4657: 2296.8501, 44.4658: 2061.2114, 53.9272: 2061.2114, 53.9273: 2059.2326, 53.9278: 2053.1578, 82.7036: 2051.9287, 92.4212: 2051.6594, 131.614: 2051.6594, 131.6141: 2032.6123, 141.3403: 2031.1739, 160.9289: 2029.8256, 171.1977: 2023.253, 181.1285: 2023.253, 181.1286: 1995.2632, 181.1287: 1992.5383, 181.1291: 1986.324, 191.1437: 1983.594, 221.4958: 1982.1552, 274.7985: 1982.1552, 274.7986: 1978.9522, 286.0577: 1971.9314, 328.5615: 1971.9314, 328.5616: 1953.0861, 360.9893: 1950.2616, 394.1085: 1950.2616, 394.1086: 1948.9993, 405.2213: 1948.9993, 405.2214: 1947.8298, 450.5544: 1946.916, 461.9489: 1946.916, 461.949: 1940.439, 484.9532: 1937.574, 508.5703: 1937.574, 508.5704: 1937.1744, 544.1744: 1304.7022, 580.3203: 1303.6824, 580.3204: 1299.7735, 592.4823: 1299.7735}"/>
		<Output spanningTreeLength="1274.766" tourCost="2208.707" timeTaken="598.629" pruned="32" ellipsesRemaining="8" costOverTime="{26.1353: 2105.8715, 35.4437: 2105.8715, 35.4463: 2096.4224, 35.4575: 2095.6688, 54.0299: 2091.9888, 63.347: 2085.4926, 72.8208: 2085.4926, 72.8209: 1389.9062, 82.3121: 1389.7725, 82.3122: 1388.9428, 91.8275: 1388.9428, 91.8276: 1363.686, 91.8277: 1363.686, 91.8278: 1362.8425, 101.3181: 1360.1923, 110.9383: 1356.9598, 130.1399: 1339.972, 139.8326: 1339.6961, 139.8327: 1337.9551, 149.5335: 1324.9622, 159.3313: 1324.2165, 159.3314: 1324.0756, 169.1368: 1324.0756, 169.1369: 1319.6655, 178.9879: 1319.6655, 178.988: 1319.229, 198.9586: 1311.0335, 209.0734: 1311.0335, 209.0735: 1291.3667, 239.8002: 1290.8544, 270.7741: 1290.8544, 270.7742: 1290.6121, 281.1936: 1288.4486, 355.9747: 1288.4486, 355.9749: 1288.1332, 399.993: 1279.6777, 433.9276: 1274.7664, 598.6263: 1274.7664}"/>
		<Output spanningTreeLength="1282.045" tourCost="2196.409" timeTaken="601.444" pruned="31" ellipsesRemaining="9" costOverTime="{25.9264: 1676.4652, 35.2192: 1676.4652, 35.2273: 1632.0497, 35.2301: 1632.0497, 35.2302: 1627.4709, 44.5863: 1512.3292, 44.5864: 1511.4915, 53.8589: 1401.7761, 63.1956: 1380.5015, 72.7743: 1380.5015, 72.7744: 1380.4639, 82.3663: 1380.4639, 82.3664: 1380.2679, 92.0578: 1377.0532, 92.0579: 1369.1553, 101.661: 1368.4155, 111.2925: 1361.3049, 120.926: 1361.3049, 120.9261: 1321.8887, 130.5964: 1319.704, 150.2706: 1318.1289, 160.0555: 1316.3047, 160.0556: 1315.6847, 189.8127: 1315.6847, 189.8128: 1302.9991, 189.8129: 1296.7023, 368.7177: 1287.9947, 413.4888: 1286.8987, 424.6806: 1286.8987, 424.6807: 1286.3866, 493.7355: 1284.2877, 517.0761: 1282.1044, 565.0865: 1282.1044, 565.0866: 1282.045, 598.1884: 1282.045}"/>
		<Output spanningTreeLength="1288.22" tourCost="2195.761" timeTaken="593.987" pruned="31" ellipsesRemaining="9" costOverTime="{39.2126: 2086.667, 58.2538: 2084.8968, 67.5757: 2082.2025, 76.9585: 2082.2025, 76.9586: 2069.9049, 76.9591: 2065.1829, 86.4073: 2060.31, 86.4079: 2058.978, 95.8686: 2056.8984, 105.396: 2046.7215, 114.9525: 2046.7215, 114.9526: 2040.4252, 124.9144: 2040.4252, 124.9145: 2026.2134, 124.9175: 2026.2134, 124.9176: 1882.693, 134.5957: 1881.802, 174.1239: 1859.5693, 184.0949: 1859.5693, 184.095: 1831.8705, 184.0953: 1829.1, 194.2846: 1784.677, 194.2847: 1783.5105, 225.1386: 1783.5105, 225.1387: 1774.7614, 256.3628: 1774.7614, 256.3629: 1747.8099, 309.216: 1747.8099, 309.2161: 1742.9132, 353.0614: 1613.0303, 375.1018: 1377.3412, 396.9065: 1376.9956, 430.682: 1376.9956, 430.6821: 1344.7235, 453.2072: 1344.7235, 453.2073: 1292.8551, 487.5703: 1292.1935, 522.5506: 1289.485, 534.1664: 1288.2198, 593.985: 1288.2198}"/>
		<Output spanningTreeLength="1261.303" tourCost="2188.227" timeTaken="593.099" pruned="32" ellipsesRemaining="8" costOverTime="{12.9485: 1788.3487, 12.9486: 1781.1822, 22.252: 1765.1068, 22.2521: 1550.4354, 31.4204: 1517.0977, 31.4205: 1514.9019, 31.423: 1514.7831, 40.6964: 1514.7831, 40.6965: 1395.9142, 40.6966: 1394.3714, 40.6991: 1393.3537, 49.9918: 1340.3987, 68.5228: 1339.5598, 77.875: 1339.3775, 87.2765: 1339.3775, 87.2766: 1338.7716, 125.3237: 1328.1735, 134.964: 1326.9262, 144.65: 1326.9262, 144.6501: 1326.0341, 154.3588: 1326.0341, 154.3589: 1320.448, 164.2193: 1318.763, 174.0843: 1318.763, 174.0844: 1315.3429, 183.9986: 1311.2406, 193.9834: 1311.2406, 193.9835: 1310.6883, 254.8362: 1310.6883, 254.8363: 1309.2939, 265.2765: 1309.2939, 265.2766: 1288.8116, 307.2875: 1281.1226, 317.9713: 1274.5122, 339.5068: 1267.6311, 372.2444: 1261.3026, 593.0968: 1261.3026}"/>
		<Output spanningTreeLength="1271.2" tourCost="2206.659" timeTaken="600.205" pruned="32" ellipsesRemaining="8" costOverTime="{26.0426: 1800.5003, 35.2674: 1800.5003, 35.2675: 1682.1463, 35.2702: 1682.1463, 35.2703: 1647.847, 44.4842: 1482.9909, 53.9105: 1453.7139, 63.1941: 1453.7139, 63.1942: 1453.7012, 63.1943: 1453.7012, 63.1944: 1440.9459, 72.7093: 1440.9459, 72.7094: 1428.9734, 82.0813: 1428.9734, 82.0814: 1389.4735, 139.9147: 1302.5125, 189.8699: 1293.1015, 199.8328: 1290.0945, 220.0972: 1285.2048, 230.1944: 1285.2048, 230.1945: 1282.185, 271.4342: 1279.0058, 281.8888: 1277.2916, 334.8997: 1277.2916, 334.8998: 1277.1759, 345.7109: 1272.5209, 504.3652: 1272.5209, 504.3653: 1271.8576, 528.0556: 1271.8576, 528.0557: 1271.1998, 596.9579: 1271.1998}"/>
		<Output spanningTreeLength="1271.591" tourCost="2193.698" timeTaken="599.763" pruned="31" ellipsesRemaining="9" costOverTime="{12.9075: 2274.7153, 22.2312: 2273.5229, 22.2313: 2167.9575, 31.5302: 2015.7868, 31.5361: 1972.4661, 69.3581: 1972.2593, 107.8206: 1972.2593, 107.8207: 1922.0414, 107.8209: 1915.9411, 127.0363: 1906.2741, 137.0737: 1904.4944, 137.0741: 1902.8995, 146.7929: 1898.2918, 156.5875: 1898.0459, 166.6941: 1782.5615, 227.5345: 1770.1733, 249.0567: 1651.6596, 457.061: 1293.0891, 480.1105: 1290.0165, 491.8689: 1274.6277, 575.3931: 1272.4396, 599.7599: 1271.591, 599.76: 1271.591}"/>
		<Output spanningTreeLength="1271.086" tourCost="2204.552" timeTaken="597.643" pruned="31" ellipsesRemaining="9" costOverTime="{25.8863: 2260.9442, 35.1959: 2260.9442, 35.204: 2079.6326, 35.2203: 2073.0793, 44.4545: 2072.5342, 53.8693: 2072.5342, 53.8694: 2043.9451, 53.8699: 2040.7467, 63.1629: 2022.4878, 72.8634: 2000.93, 101.2739: 1375.9697, 110.8324: 1375.9697, 110.8325: 1365.3222, 120.3946: 1365.3222, 120.3947: 1364.9065, 130.052: 1361.6082, 149.4447: 1361.6082, 149.4448: 1343.4578, 159.171: 1341.5724, 168.9791: 1341.1329, 178.8761: 1341.1329, 178.8762: 1340.8352, 198.8114: 1338.1925, 218.9528: 1338.1185, 229.1649: 1337.743, 229.165: 1316.7382, 239.3778: 1316.729, 249.6593: 1316.729, 249.6594: 1316.6015, 260.0752: 1296.4203, 291.3291: 1296.4203, 291.3292: 1295.5486, 312.5021: 1295.5486, 312.5022: 1290.9659, 323.2495: 1289.7803, 366.585: 1289.7803, 366.5851: 1280.0566, 388.6521: 1280.0566, 388.6522: 1276.3622, 549.7164: 1275.9382, 573.6052: 1275.9382, 573.6053: 1271.0865, 597.6402: 1271.0865}"/>
		<Output spanningTreeLength="1259.782" tourCost="2184.495" timeTaken="602.701" pruned="32" ellipsesRemaining="8" costOverTime="{39.1826: 2051.2664, 48.4387: 2051.2664, 48.4466: 1967.596, 48.4468: 1336.5762, 67.1637: 1336.5762, 67.1639: 1335.282, 67.164: 1333.6225, 86.3075: 1315.9603, 96.0262: 1315.9603, 96.0263: 1312.5876, 115.074: 1304.6417, 134.3157: 1290.2737, 173.4665: 1290.2737, 173.4666: 1288.7599, 223.7544: 1285.2491, 275.1761: 1285.2491, 275.1762: 1281.5537, 317.2721: 1281.5537, 317.2722: 1281.1844, 360.6439: 1275.0175, 360.644: 1273.3148, 438.3626: 1272.1856, 542.7105: 1270.5029, 554.6355: 1260.7899, 590.6926: 1260.7899, 590.6927: 1259.7816, 599.4475: 1259.7816}"/>
		<Output spanningTreeLength="1267.005" tourCost="2174.313" timeTaken="595.646" pruned="32" ellipsesRemaining="8" costOverTime="{12.8867: 2203.9237, 22.137: 2132.6977, 31.3768: 2132.6977, 31.3769: 2128.645, 31.377: 2121.3947, 31.3774: 2111.3944, 40.7269: 2111.3944, 40.727: 2106.1641, 49.9835: 2057.0785, 49.9867: 2049.2813, 69.1952: 2040.1414, 69.1956: 2034.5102, 78.906: 2034.5102, 78.9061: 1418.0575, 98.0553: 1417.6853, 107.5491: 1405.6459, 117.1242: 1405.6459, 117.1243: 1377.8426, 117.1244: 1373.796, 126.7475: 1373.796, 126.7476: 1328.2217, 126.7477: 1324.2312, 136.5415: 1316.9275, 196.0008: 1316.9275, 196.0009: 1312.6338, 206.1155: 1283.1647, 226.4035: 1278.3824, 277.8708: 1276.0047, 320.1116: 1276.0047, 320.1117: 1272.2542, 385.5256: 1271.8844, 487.7582: 1267.0053, 595.6437: 1267.0053}"/>
		<Output spanningTreeLength="1290.296" tourCost="2203.358" timeTaken="596.131" pruned="32" ellipsesRemaining="8" costOverTime="{12.9729: 2583.5286, 22.0891: 2583.5286, 22.0972: 2576.9743, 22.1083: 2576.9743, 22.1084: 2258.9418, 31.2719: 2181.9118, 31.2751: 2181.9118, 31.2752: 2177.3115, 40.47: 2148.536, 40.4706: 2079.3876, 50.0161: 2079.3876, 50.0162: 2056.2647, 50.0168: 2054.4675, 59.4785: 2054.4675, 59.4786: 2042.0511, 59.4792: 2028.1349, 68.9958: 2012.7974, 68.9964: 2012.6067, 78.4772: 2012.6067, 78.4773: 2004.6168, 87.9521: 2004.6168, 87.9522: 1961.6985, 97.4573: 1959.1465, 116.5785: 1845.4823, 126.1917: 1840.0242, 135.9014: 1839.1391, 145.8096: 1838.7382, 185.8291: 1837.4633, 195.8543: 1837.4633, 195.8544: 1836.5009, 247.0511: 1829.335, 288.8268: 1829.335, 288.8269: 1827.323, 310.2146: 1317.0625, 310.2147: 1315.2153, 331.9214: 1306.938, 342.6646: 1301.2164, 353.8562: 1301.2164, 353.8563: 1295.7437, 386.7667: 1294.79, 397.8653: 1292.4073, 500.3662: 1292.4073, 500.3663: 1292.0414, 535.6719: 1292.0414, 535.672: 1291.3675, 584.028: 1290.2956, 596.1284: 1290.2956}"/>
	</Ripple>
	<PRMbaseline>
		<Output spanningTreeLength="1348.223" tourCost="2696.446" timeTaken="604.135" costOverTime="{36.3315: 2385.9609, 48.5366: 2243.1501, 60.8017: 2243.1501, 60.8018: 2236.5666, 97.8809: 2193.0822, 110.3472: 2193.0822, 110.3473: 2026.482, 135.4908: 2024.8151, 148.1243: 2004.8163, 160.9106: 1956.0705, 186.6094: 1942.3279, 238.6819: 1942.3279, 238.682: 1929.5353, 251.8364: 1452.7815, 291.9547: 1447.5981, 305.4641: 1377.5388, 319.0316: 1377.5388, 319.0317: 1368.3989, 401.8808: 1348.8046, 430.3907: 1348.223, 576.9918: 1348.223}"/>
		<Output spanningTreeLength="1304.602" tourCost="2609.204" timeTaken="607.808" costOverTime="{24.2382: 2052.9469, 36.4679: 2032.0908, 48.6703: 1989.5424, 60.9175: 1982.1574, 73.2257: 1897.0031, 98.0606: 1897.0031, 98.0607: 1876.0816, 110.557: 1857.6322, 135.7468: 1849.2555, 148.4419: 1839.8827, 174.0119: 1404.5449, 186.8853: 1400.0847, 199.8554: 1394.4504, 212.8819: 1386.7316, 226.0083: 1331.8712, 265.8164: 1330.849, 279.2215: 1329.2596, 361.549: 1324.2286, 491.4115: 1324.2286, 491.4116: 1310.5923, 506.1413: 1307.5911, 536.0901: 1304.6018, 581.4678: 1304.6018}"/>
		<Output spanningTreeLength="1285.061" tourCost="2570.122" timeTaken="607.101" costOverTime="{24.171: 2149.2492, 36.3198: 2018.0805, 48.5282: 1359.1605, 60.7903: 1354.2619, 73.1236: 1352.5362, 85.5116: 1352.5362, 85.5117: 1346.7159, 110.4628: 1343.4738, 148.4502: 1343.4738, 148.4503: 1343.4437, 187.1473: 1325.5943, 200.1557: 1325.5943, 200.1558: 1323.3931, 239.6626: 1323.3931, 239.6627: 1317.7087, 306.8786: 1298.8064, 362.1787: 1288.339, 404.3801: 1288.339, 404.3802: 1286.0982, 432.9267: 1286.0362, 550.395: 1285.0609, 580.6408: 1285.0609}"/>
		<Output spanningTreeLength="1316.473" tourCost="2632.946" timeTaken="609.243" costOverTime="{24.184: 2107.4159, 48.5529: 2105.3291, 60.8227: 2057.348, 73.333: 2030.4759, 85.7253: 2012.0618, 98.1858: 1992.3574, 136.0739: 1977.1649, 148.7903: 1359.7254, 174.4763: 1358.622, 200.8299: 1334.5147, 214.0915: 1334.4339, 227.337: 1334.4339, 227.3371: 1327.6306, 240.563: 1327.1049, 253.8012: 1318.7859, 321.1428: 1318.7859, 321.1429: 1317.6445, 362.6397: 1317.3088, 376.5933: 1316.473, 581.8953: 1316.473}"/>
		<Output spanningTreeLength="1314.016" tourCost="2628.032" timeTaken="609.513" costOverTime="{12.0883: 2064.6248, 24.1845: 2046.1803, 36.3385: 2044.8478, 48.539: 1959.7997, 60.8225: 1495.341, 73.1409: 1414.8348, 85.5304: 1382.8264, 97.9652: 1382.1075, 123.0602: 1381.6428, 161.5134: 1340.3919, 174.3377: 1337.4011, 200.3107: 1319.5495, 226.5738: 1318.6324, 239.7687: 1317.2592, 348.8169: 1316.9358, 477.2747: 1314.8647, 522.0207: 1314.8647, 522.0208: 1314.5646, 551.8399: 1314.0159, 582.11: 1314.0159}"/>
		<Output spanningTreeLength="1291.24" tourCost="2582.48" timeTaken="607.596" costOverTime="{48.5263: 2013.2185, 60.7858: 1998.1434, 73.1047: 1997.1461, 97.9195: 1996.5201, 110.4242: 1996.5201, 110.4243: 1995.075, 122.9869: 1995.075, 122.987: 1995.0045, 161.0682: 1975.4575, 173.9767: 1974.9811, 186.906: 1970.2553, 199.9343: 1960.2107, 252.7369: 1949.5208, 320.27: 1949.5208, 320.2701: 1946.5052, 334.0203: 1939.1896, 348.0589: 1937.9801, 361.9432: 1339.4068, 432.8537: 1335.642, 447.2313: 1329.7406, 506.2885: 1329.7406, 506.2886: 1324.579, 521.0613: 1320.9379, 566.402: 1320.9379, 566.4021: 1291.2398, 581.54: 1291.2398}"/>
		<Output spanningTreeLength="1305.056" tourCost="2610.111" timeTaken="609.966" costOverTime="{98.0123: 1401.79, 110.7376: 1370.123, 123.3379: 1319.0026, 390.9462: 1319.0026, 390.9463: 1311.7546, 507.1994: 1311.7546, 507.1995: 1305.0556, 582.4857: 1305.0556}"/>
		<Output spanningTreeLength="1306.079" tourCost="2612.158" timeTaken="605.954" costOverTime="{36.3028: 2036.6827, 48.5011: 2036.6827, 48.5012: 2035.2305, 60.7572: 2031.5083, 73.0651: 2005.8103, 85.4461: 2005.8103, 85.4462: 2003.0373, 97.877: 1385.9369, 110.3784: 1365.6855, 122.9663: 1365.3636, 148.3253: 1361.9393, 161.0968: 1349.0978, 173.9727: 1349.0978, 173.9728: 1330.2938, 186.9824: 1326.6666, 213.057: 1321.3695, 226.201: 1321.3695, 226.2011: 1314.5668, 293.2957: 1311.5286, 362.0652: 1311.359, 376.1246: 1311.359, 376.1247: 1311.1774, 418.2588: 1310.0259, 476.0438: 1306.0788, 579.8658: 1306.0788}"/>
		<Output spanningTreeLength="1294.783" tourCost="2589.566" timeTaken="608.744" costOverTime="{24.1747: 2126.303, 36.3308: 2126.303, 36.3309: 2104.6743, 48.5325: 2104.6064, 60.8097: 2104.6064, 60.8098: 1979.5442, 73.1376: 1979.5442, 73.1377: 1968.0161, 85.5302: 1371.9007, 110.4954: 1366.2297, 123.1362: 1326.8786, 135.7916: 1322.5832, 161.2985: 1319.7115, 187.0758: 1311.5362, 213.2298: 1302.5209, 279.8319: 1295.86, 306.9685: 1295.1551, 491.9593: 1295.1551, 491.9594: 1294.783, 582.3867: 1294.783}"/>
		<Output spanningTreeLength="1307.42" tourCost="2614.84" timeTaken="608.396" costOverTime="{24.1804: 2406.4369, 36.3464: 2406.4369, 36.3465: 2231.4902, 48.5615: 2171.3807, 60.8462: 2163.6268, 73.1877: 1575.483, 85.5714: 1375.2357, 123.1725: 1374.2624, 135.8048: 1349.3404, 148.5319: 1349.3404, 148.532: 1345.3708, 213.4095: 1345.3708, 213.4096: 1328.0917, 253.3025: 1327.8151, 307.3926: 1327.4156, 321.1375: 1322.6946, 362.8922: 1314.2009, 376.8937: 1313.6968, 507.65: 1307.42, 582.9395: 1307.42}"/>
		<Output spanningTreeLength="1323.335" tourCost="2646.67" timeTaken="609.85" costOverTime="{24.1747: 2218.4861, 36.3318: 2218.4861, 36.3319: 2075.7657, 48.539: 2075.7657, 48.5391: 2068.9016, 60.8138: 2068.9016, 60.8139: 1426.3926, 73.1653: 1422.1412, 85.5795: 1418.2367, 98.0453: 1392.3912, 110.5621: 1389.2251, 135.8362: 1389.2251, 135.8363: 1388.6832, 187.2346: 1388.6832, 187.2347: 1363.3285, 239.9499: 1360.4828, 253.2761: 1359.1628, 294.0339: 1357.3872, 348.9506: 1333.6156, 363.0316: 1329.2469, 377.2628: 1329.2469, 377.2629: 1328.2485, 405.7152: 1323.335, 583.0977: 1323.335}"/>
		<Output spanningTreeLength="1304.002" tourCost="2608.003" timeTaken="610.934" costOverTime="{24.1836: 2073.5297, 36.3379: 1995.7529, 85.5749: 1986.1542, 98.0422: 1976.1533, 110.6199: 1976.1533, 110.62: 1969.4344, 123.2272: 1969.4344, 123.2273: 1962.9947, 135.9112: 1962.9947, 135.9113: 1957.5125, 148.6531: 1957.5125, 148.6532: 1954.2554, 174.4239: 1951.356, 187.38: 1951.356, 187.3801: 1949.9627, 253.404: 1949.9627, 253.4041: 1367.5497, 266.8784: 1367.5497, 266.8785: 1362.1109, 321.4947: 1362.1109, 321.4948: 1336.0289, 335.3276: 1334.9483, 349.2556: 1334.9483, 349.2557: 1321.2607, 463.5415: 1321.2607, 463.5416: 1304.0016, 584.0184: 1304.0016}"/>
		<Output spanningTreeLength="1279.857" tourCost="2559.713" timeTaken="608.802" costOverTime="{36.3412: 1991.3324, 48.5588: 1991.3324, 48.5589: 1989.5766, 60.8347: 1343.2802, 73.1778: 1343.2802, 73.1779: 1343.0945, 85.6414: 1340.1045, 98.1018: 1340.1045, 98.1019: 1325.4054, 110.6356: 1324.8643, 161.5817: 1314.5579, 187.4627: 1314.5579, 187.4628: 1309.7139, 253.5021: 1305.3091, 280.4917: 1305.3091, 280.4918: 1290.7344, 294.1055: 1287.2839, 335.3204: 1286.9398, 363.2197: 1286.9398, 363.2198: 1279.8567, 582.1715: 1279.8567}"/>
		<Output spanningTreeLength="1311.254" tourCost="2622.509" timeTaken="610.162" costOverTime="{12.0719: 2215.7911, 24.2118: 2160.231, 36.4097: 2035.243, 48.6265: 1980.6593, 60.897: 1980.6593, 60.8971: 1353.451, 73.416: 1346.2746, 98.2567: 1345.2123, 110.7749: 1331.4135, 349.3504: 1315.0866, 377.292: 1312.0171, 448.9836: 1311.8762, 478.1969: 1311.2543, 582.9674: 1311.2543}"/>
		<Output spanningTreeLength="1283.182" tourCost="2566.365" timeTaken="611.091" costOverTime="{24.1915: 2043.8609, 36.3561: 2039.8393, 48.5783: 2020.0615, 73.2118: 2006.7231, 85.6212: 2006.7231, 85.6213: 1960.6323, 110.6293: 1448.5266, 135.922: 1448.5266, 135.9221: 1447.0611, 161.5196: 1445.0825, 174.4258: 1441.5922, 187.3936: 1410.8338, 226.7725: 1410.8338, 226.7726: 1390.4917, 239.9991: 1390.4917, 239.9992: 1380.8454, 266.8318: 1305.9838, 294.0291: 1285.1135, 493.4654: 1283.1823, 584.572: 1283.1823}"/>
		<Output spanningTreeLength="1313.897" tourCost="2627.794" timeTaken="608.495" costOverTime="{24.1817: 2038.1418, 36.3468: 2038.1418, 36.3469: 2032.1907, 48.5732: 2004.8217, 60.8373: 2004.8217, 60.8374: 1986.9109, 85.5889: 1983.1827, 110.6166: 1981.0443, 123.21: 1981.0443, 123.2101: 1975.0538, 135.8734: 1965.9934, 148.6058: 1965.2001, 161.4127: 1925.1615, 187.2527: 1339.5242, 200.2901: 1339.5242, 200.2902: 1318.5772, 320.9151: 1314.1728, 448.0399: 1314.0908, 477.2713: 1313.897, 582.4149: 1313.897}"/>
		<Output spanningTreeLength="1304.013" tourCost="2608.026" timeTaken="611.683" costOverTime="{12.0776: 2409.429, 24.1809: 2409.429, 24.181: 2171.6305, 36.334: 2171.6305, 36.3341: 2039.4789, 60.8249: 2030.2309, 73.1778: 2002.5448, 98.0752: 1976.7454, 110.6263: 1976.7454, 110.6264: 1974.174, 123.2417: 1974.0697, 136.0252: 1971.4996, 161.6026: 1971.4996, 161.6027: 1967.8715, 174.4831: 1963.887, 187.4547: 1962.6671, 253.7658: 1370.4894, 364.0628: 1307.066, 378.0524: 1305.8103, 392.284: 1304.0128, 584.6869: 1304.0128}"/>
		<Output spanningTreeLength="1347.091" tourCost="2694.183" timeTaken="610.12" costOverTime="{24.1818: 2369.4911, 36.3447: 2177.0355, 48.572: 2177.0355, 48.5721: 2163.7464, 60.8594: 2016.1807, 73.1997: 2000.8236, 85.6161: 1989.2951, 98.0894: 1977.0067, 123.2516: 1967.9452, 148.6763: 1965.8562, 187.3809: 1965.7717, 200.4153: 1965.7717, 200.4154: 1480.0666, 240.1083: 1480.0666, 240.1084: 1479.8185, 266.9172: 1426.9136, 307.6713: 1425.5921, 335.3054: 1422.1266, 349.2694: 1405.393, 363.2088: 1395.7301, 391.4884: 1381.4912, 552.9099: 1347.0915, 583.5754: 1347.0915}"/>
		<Output spanningTreeLength="1300.163" tourCost="2600.326" timeTaken="610.517" costOverTime="{48.5481: 2079.3539, 60.8114: 2032.6513, 73.1409: 2032.4271, 85.5796: 2029.7027, 98.031: 1361.6711, 110.6043: 1361.0651, 123.2134: 1357.1776, 135.8935: 1356.5226, 174.3807: 1335.3794, 200.4126: 1335.3794, 200.4127: 1307.8971, 266.7541: 1300.163, 584.0719: 1300.163}"/>
		<Output spanningTreeLength="1309.957" tourCost="2619.915" timeTaken="612.978" costOverTime="{98.0709: 1359.8955, 123.3586: 1359.8955, 123.3587: 1327.6497, 148.848: 1319.1723, 161.7212: 1316.4587, 350.0283: 1316.4587, 350.0284: 1314.5062, 364.0964: 1311.6303, 479.797: 1311.6303, 479.7971: 1309.9575, 585.4359: 1309.9575}"/>
		<Output spanningTreeLength="1287.199" tourCost="2574.399" timeTaken="611.57" costOverTime="{24.1904: 2143.2265, 36.3343: 2136.1002, 48.5295: 2043.2037, 60.8006: 2043.2037, 60.8007: 2024.4947, 73.1408: 2024.4947, 73.1409: 2021.26, 85.5664: 1953.9256, 110.6: 1952.3474, 161.8332: 1933.5686, 174.9538: 1933.5686, 174.9539: 1902.5454, 214.1008: 1333.0197, 281.1582: 1308.9082, 294.7658: 1308.441, 350.5218: 1307.8146, 422.0838: 1307.8146, 422.0839: 1287.1994, 585.4093: 1287.1994}"/>
		<Output spanningTreeLength="1324.652" tourCost="2649.304" timeTaken="616.478" costOverTime="{24.1924: 2183.8063, 36.3511: 2154.0949, 48.5543: 2154.0949, 48.5544: 2038.1949, 60.8504: 1990.5446, 73.2551: 1986.4479, 98.1241: 1983.4, 187.8857: 1365.0101, 200.9264: 1336.8653, 294.2424: 1330.3553, 322.1941: 1329.8755, 336.3383: 1329.8001, 572.1863: 1325.5303, 587.6105: 1325.5303}"/>
		<Output spanningTreeLength="1300.3" tourCost="2600.6" timeTaken="607.794" costOverTime="{36.3539: 2441.6477, 48.6064: 2281.5634, 60.8958: 2167.3087, 73.2252: 1534.1844, 85.6251: 1415.0927, 98.098: 1406.3204, 110.6177: 1405.8214, 148.7729: 1384.0235, 161.5405: 1358.3592, 200.4057: 1357.5916, 239.8059: 1357.5916, 239.806: 1356.1426, 253.1082: 1352.4586, 279.9408: 1351.8081, 334.5662: 1348.3163, 348.3573: 1347.6572, 376.2636: 1344.712, 418.7868: 1336.7886, 491.4027: 1333.3492, 566.2212: 1300.3001, 581.4393: 1300.3001}"/>
		<Output spanningTreeLength="1311.582" tourCost="2623.164" timeTaken="611.972" costOverTime="{24.177: 2104.1764, 36.3335: 1459.5284, 48.5641: 1453.4916, 73.2193: 1440.4659, 85.641: 1440.4659, 85.6411: 1428.3396, 98.129: 1426.3795, 123.3668: 1392.037, 136.0479: 1378.3703, 161.6092: 1357.1431, 174.5553: 1330.1807, 349.4913: 1326.8738, 377.81: 1322.7534, 435.5958: 1318.8707, 479.6651: 1311.5819, 585.7359: 1311.5819}"/>
		<Output spanningTreeLength="1315.65" tourCost="2631.301" timeTaken="612.974" costOverTime="{24.1819: 2173.1078, 36.3402: 2173.1078, 36.3403: 2128.8526, 48.5557: 2101.2611, 60.8368: 2063.7411, 73.2075: 2023.8172, 85.6156: 2015.0925, 98.0918: 2015.0925, 98.0919: 2005.9172, 110.648: 1996.3337, 123.2919: 1995.9949, 135.9818: 1992.7618, 148.7556: 1991.9593, 174.5137: 1982.628, 187.5019: 1455.1971, 253.6759: 1455.1971, 253.676: 1398.4334, 280.7395: 1370.7949, 294.3967: 1370.506, 321.9228: 1348.3623, 364.1041: 1348.3623, 364.1042: 1348.1968, 378.2423: 1326.3847, 464.925: 1326.3847, 464.9251: 1325.97, 524.3189: 1323.7777, 570.2331: 1316.0109, 585.5142: 1316.0109}"/>
		<Output spanningTreeLength="1277.518" tourCost="2555.037" timeTaken="608.606" costOverTime="{24.1755: 2195.8789, 36.3308: 2195.8789, 36.3309: 2194.9244, 48.5498: 2158.5307, 60.8239: 2158.5307, 60.824: 2013.9529, 73.167: 1959.5581, 85.5657: 1959.5581, 85.5658: 1933.0445, 110.5812: 1776.0266, 135.9044: 1776.0266, 135.9045: 1346.1351, 148.6711: 1345.5974, 161.4808: 1337.9719, 174.4021: 1304.5448, 213.517: 1304.5448, 213.5171: 1286.2462, 307.5989: 1278.9745, 321.3416: 1278.9745, 321.3417: 1278.657, 419.6558: 1278.0803, 462.995: 1278.0803, 462.9951: 1277.5184, 582.828: 1277.5184}"/>
		<Output spanningTreeLength="1308.427" tourCost="2616.855" timeTaken="610.392" costOverTime="{36.3303: 2290.9009, 48.5467: 1998.0953, 85.566: 1394.2317, 98.058: 1394.2317, 98.0581: 1392.3166, 123.2012: 1365.0139, 187.3001: 1358.1098, 293.847: 1358.1098, 293.8471: 1352.9309, 349.0323: 1350.5794, 377.2089: 1347.7709, 405.6389: 1340.7381, 420.0135: 1340.7381, 420.0136: 1318.859, 508.173: 1318.859, 508.1731: 1315.0411, 584.0781: 1315.0411}"/>
		<Output spanningTreeLength="1293.76" tourCost="2587.519" timeTaken="611.074" costOverTime="{12.0779: 1345.5417, 24.1798: 1341.1146, 36.3391: 1324.5909, 48.5571: 1324.5909, 48.5572: 1323.0871, 60.8326: 1321.6677, 73.1682: 1320.7666, 85.5871: 1318.4284, 98.0593: 1318.0052, 226.9688: 1318.0052, 226.9689: 1316.8542, 240.2923: 1309.7306, 378.0255: 1307.2525, 435.3002: 1302.7028, 479.273: 1302.7028, 479.2731: 1299.5138, 494.284: 1293.7597, 585.055: 1293.7597}"/>
		<Output spanningTreeLength="1322.618" tourCost="2645.235" timeTaken="612.644" costOverTime="{24.177: 1378.2849, 36.3341: 1372.0439, 48.5624: 1371.7127, 60.8368: 1359.6434, 73.1882: 1350.897, 110.6731: 1350.8805, 136.0242: 1349.9645, 161.5783: 1347.2185, 267.1156: 1347.2185, 267.1157: 1347.0683, 335.705: 1343.4437, 363.6746: 1338.2965, 392.1519: 1330.6183, 406.4864: 1323.8912, 449.9441: 1322.6175, 584.853: 1322.6175}"/>
		<Output spanningTreeLength="1331.83" tourCost="2663.661" timeTaken="610.815" costOverTime="{24.1801: 2229.3228, 36.346: 2064.7808, 48.5733: 2024.4305, 60.8447: 1960.3623, 73.1944: 1953.2742, 85.5958: 1948.4354, 110.6132: 1947.8681, 161.6451: 1947.8558, 226.8825: 1356.5234, 240.1559: 1355.8261, 253.4866: 1355.8261, 253.4867: 1354.1688, 266.9352: 1352.2454, 349.1907: 1352.2454, 349.1908: 1345.2464, 363.2114: 1342.3906, 391.431: 1339.4611, 405.6605: 1339.4611, 405.6606: 1337.2118, 419.9089: 1332.68, 449.1112: 1332.68, 449.1113: 1331.8305, 583.733: 1331.8305}"/>
		<Output spanningTreeLength="1299.048" tourCost="2598.095" timeTaken="612.078" costOverTime="{24.198: 2043.4747, 36.3549: 2005.1371, 48.5862: 1951.0301, 73.2118: 1951.0301, 73.2119: 1949.5227, 110.6599: 1941.3003, 148.8169: 1356.7868, 174.6773: 1328.9477, 227.0282: 1326.7783, 280.7222: 1326.7783, 280.7223: 1309.7988, 350.1577: 1309.7988, 350.1578: 1308.4152, 364.1979: 1303.0238, 406.6846: 1300.7788, 449.951: 1300.4451, 479.399: 1299.5778, 569.7835: 1299.0476, 584.9978: 1299.0476}"/>
		<Output spanningTreeLength="1317.604" tourCost="2635.209" timeTaken="611.852" costOverTime="{12.0807: 2147.1023, 24.1842: 2054.2161, 36.3409: 2011.036, 48.5599: 1999.6606, 60.8539: 1998.8587, 73.193: 1998.8587, 73.1931: 1996.905, 85.5989: 1994.9493, 98.0893: 1983.2683, 110.6526: 1983.2683, 110.6527: 1981.7755, 123.2774: 1977.6182, 135.9473: 1972.2049, 148.7075: 1972.2049, 148.7076: 1971.5065, 161.65: 1971.5065, 161.6501: 1961.1867, 174.5964: 1961.1867, 174.5965: 1372.8343, 200.655: 1372.8343, 200.6551: 1371.7521, 280.7168: 1338.5114, 294.4054: 1338.5114, 294.4055: 1337.2153, 349.8193: 1337.2153, 349.8194: 1321.3465, 406.4435: 1318.6149, 464.5151: 1318.6149, 464.5152: 1317.6043, 584.9768: 1317.6043}"/>
		<Output spanningTreeLength="1321.269" tourCost="2642.538" timeTaken="614.411" costOverTime="{12.077: 2066.1979, 24.185: 2014.2074, 36.3503: 2014.2074, 36.3504: 1997.9038, 48.5715: 1984.0886, 73.2432: 1981.2508, 85.6439: 1980.0222, 98.1236: 1973.826, 110.7003: 1967.0481, 123.3749: 1962.4501, 136.1029: 1943.3454, 161.7375: 1937.1125, 174.6517: 1937.1125, 174.6518: 1355.3389, 187.6395: 1352.9448, 200.7268: 1352.9448, 200.7269: 1352.6859, 213.8813: 1352.6859, 213.8814: 1341.8598, 240.4398: 1339.5371, 280.9557: 1333.8456, 294.5902: 1329.0756, 350.1253: 1329.0756, 350.1254: 1325.4038, 450.4653: 1321.4763, 465.2006: 1321.2688, 586.0501: 1321.2688}"/>
		<Output spanningTreeLength="1308.907" tourCost="2617.814" timeTaken="611.833" costOverTime="{36.4113: 2204.582, 48.6282: 2118.5811, 60.9108: 2110.1431, 73.2544: 2050.0955, 85.6642: 1996.0744, 98.1604: 1971.7537, 110.725: 1964.7818, 136.2516: 1961.1538, 161.977: 1961.1538, 161.9771: 1955.7838, 174.8945: 1932.934, 200.916: 1932.321, 254.1665: 1926.9745, 281.2637: 1921.3898, 295.0636: 1915.7434, 322.6182: 1915.6931, 350.505: 1909.7462, 378.6693: 1909.7462, 378.6694: 1908.5143, 479.6806: 1901.5701, 494.4858: 1323.6656, 509.3793: 1323.5848, 569.6741: 1323.5848, 569.6742: 1321.4935, 584.929: 1321.4935}"/>
		<Output spanningTreeLength="1303.165" tourCost="2606.33" timeTaken="611.36" costOverTime="{24.1808: 2290.373, 36.336: 2275.5959, 48.5575: 2160.8015, 60.846: 2160.8015, 60.8461: 2158.0889, 73.1853: 2038.8749, 85.599: 2038.8749, 85.5991: 2014.8239, 98.0735: 2002.2542, 110.6086: 2002.2542, 110.6087: 1972.4941, 123.2: 1369.0608, 135.9353: 1368.0937, 161.5719: 1364.4767, 213.8219: 1360.7034, 240.4254: 1339.5, 281.0043: 1339.5, 281.0044: 1338.2381, 308.315: 1330.1514, 335.9044: 1330.1514, 335.9045: 1324.7019, 378.214: 1323.375, 392.4346: 1322.4851, 421.0629: 1314.4859, 435.4286: 1314.4859, 435.4287: 1305.1741, 539.0241: 1303.1651, 584.7305: 1303.1651}"/>
		<Output spanningTreeLength="1303.433" tourCost="2606.866" timeTaken="611.295" costOverTime="{48.5558: 1373.4148, 60.8312: 1368.6131, 73.1881: 1368.6131, 73.1882: 1368.1066, 85.5989: 1343.4083, 123.2598: 1343.4083, 123.2599: 1343.3476, 135.991: 1343.3476, 135.9911: 1306.0503, 240.3916: 1305.2208, 253.7893: 1304.7417, 322.0107: 1303.4329, 584.6137: 1303.4329}"/>
		<Output spanningTreeLength="1343.526" tourCost="2687.052" timeTaken="612.994" costOverTime="{24.1873: 2110.1993, 36.3557: 2080.7045, 48.5807: 2073.0824, 60.877: 2048.7393, 73.229: 2031.4599, 98.1479: 2017.1051, 110.7017: 2015.5794, 174.5918: 2004.2206, 200.6405: 1987.4892, 267.138: 1987.4892, 267.1381: 1987.1766, 280.6971: 1986.6222, 307.9875: 1928.9202, 349.7034: 1925.0328, 392.399: 1923.7941, 450.4044: 1352.3446, 465.4094: 1352.3446, 465.4095: 1348.0111, 555.5822: 1348.0111, 555.5823: 1343.5258, 586.2359: 1343.5258}"/>
		<Output spanningTreeLength="1292.019" tourCost="2584.038" timeTaken="613.176" costOverTime="{36.3504: 2137.7292, 48.5867: 1955.4195, 60.8589: 1951.6711, 73.2157: 1942.3866, 98.1216: 1932.253, 110.6767: 1310.1381, 123.3147: 1306.8478, 350.5045: 1306.8478, 350.5046: 1305.4017, 364.6975: 1303.6171, 465.4261: 1300.8968, 524.8817: 1292.019, 585.9124: 1292.019}"/>
		<Output spanningTreeLength="1297.91" tourCost="2595.82" timeTaken="609.717" costOverTime="{12.0789: 2426.1833, 24.1829: 2400.8978, 36.3433: 2360.7584, 48.5599: 2349.9575, 60.8529: 2349.8493, 73.1869: 1467.7781, 85.6082: 1458.6067, 123.3373: 1431.7799, 136.0176: 1431.7799, 136.0177: 1407.0877, 148.7641: 1407.0877, 148.7642: 1399.878, 161.5793: 1391.4959, 174.4535: 1377.2854, 200.5326: 1364.0278, 307.8412: 1356.2453, 377.4554: 1346.6719, 391.5516: 1340.4791, 568.3061: 1340.4791, 568.3062: 1339.2518, 583.6455: 1339.2518}"/>
		<Output spanningTreeLength="1316.332" tourCost="2632.664" timeTaken="612.83" costOverTime="{73.1912: 2370.9573, 85.6013: 1960.9903, 123.2488: 1361.313, 161.5987: 1361.313, 161.5988: 1346.0286, 187.5467: 1344.2665, 213.722: 1342.7785, 280.6827: 1340.9927, 294.324: 1330.1238, 349.7175: 1324.2577, 420.9812: 1322.9367, 435.495: 1316.3497, 585.5923: 1316.3497}"/>
		<Output spanningTreeLength="1300.163" tourCost="2600.327" timeTaken="612.335" costOverTime="{24.1833: 2188.8883, 36.3403: 1999.1777, 48.5651: 1997.4067, 60.8457: 1985.5164, 73.206: 1979.6803, 98.1123: 1972.0321, 148.7635: 1972.0321, 148.7636: 1954.6471, 174.5208: 1944.0051, 187.5339: 1943.9233, 200.7661: 1353.322, 213.9016: 1340.7575, 227.1168: 1323.474, 240.4807: 1321.607, 253.9017: 1317.5687, 364.2432: 1317.2851, 495.0627: 1315.2699, 510.0201: 1307.8764, 540.1217: 1307.8764, 540.1218: 1300.1633, 586.0494: 1300.1633}"/>
		<Output spanningTreeLength="1281.017" tourCost="2562.034" timeTaken="612.068" costOverTime="{12.0733: 2017.3009, 24.1778: 2010.792, 36.3387: 2010.792, 36.3388: 2002.3345, 48.5459: 1985.7304, 85.5383: 1985.7304, 85.5384: 1979.2842, 98.0002: 1973.5777, 110.5474: 1970.7694, 135.8628: 1960.4964, 174.3961: 1960.4964, 174.3962: 1950.6359, 213.9246: 1735.6094, 253.8474: 1372.3165, 280.7781: 1337.7121, 294.4232: 1321.8831, 321.8853: 1321.8831, 321.8854: 1310.9931, 464.4892: 1288.8378, 524.3783: 1281.0168, 585.6477: 1281.0168}"/>
		<Output spanningTreeLength="1325.731" tourCost="2651.462" timeTaken="613.608" costOverTime="{24.1876: 2084.4751, 36.3511: 2046.5255, 48.5773: 2002.472, 60.868: 2000.7654, 73.2238: 1952.918, 85.6487: 1952.0085, 98.1524: 1347.7959, 110.6878: 1347.4877, 148.7847: 1347.086, 187.5616: 1347.0479, 200.6254: 1343.9446, 226.9982: 1342.7832, 267.1535: 1336.0734, 280.7524: 1336.0568, 294.3326: 1330.7637, 364.0449: 1330.2501, 406.8831: 1330.2501, 406.8832: 1326.4285, 555.2086: 1325.9297, 570.5743: 1325.7312, 586.3223: 1325.7312}"/>
		<Output spanningTreeLength="1314.558" tourCost="2629.116" timeTaken="612.749" costOverTime="{24.1817: 1474.381, 36.3433: 1424.4507, 48.5665: 1408.0326, 73.1908: 1380.475, 85.6062: 1379.1416, 98.0719: 1361.9763, 123.2463: 1360.8347, 161.5345: 1360.1172, 174.4583: 1354.5328, 240.2492: 1348.3822, 253.6314: 1347.2338, 280.6441: 1341.2875, 294.2732: 1340.1023, 321.8616: 1339.9825, 450.3898: 1333.6268, 465.0723: 1331.5342, 494.6784: 1328.1882, 524.868: 1325.7413, 540.0721: 1314.5579, 585.9338: 1314.5579}"/>
		<Output spanningTreeLength="1286.712" tourCost="2573.424" timeTaken="611.401" costOverTime="{73.1952: 1991.122, 110.6584: 1907.9194, 136.0013: 1852.987, 174.6482: 1852.0416, 187.6134: 1851.4742, 200.6939: 1300.4732, 253.7164: 1298.0363, 280.8158: 1295.3846, 391.9956: 1287.5104, 493.9926: 1287.2023, 523.9233: 1287.2023, 523.9234: 1286.7118, 585.2801: 1286.7118}"/>
		<Output spanningTreeLength="1324.058" tourCost="2648.116" timeTaken="613.891" costOverTime="{24.1857: 1995.5313, 36.3616: 1977.6065, 48.5787: 1977.6065, 48.5788: 1973.379, 60.8685: 1967.5848, 73.2286: 1967.5848, 73.2287: 1957.197, 85.6633: 1954.2821, 98.1511: 1954.2821, 98.1512: 1948.3872, 148.8035: 1942.1621, 161.6376: 1941.8394, 174.5852: 1917.9876, 187.6137: 1914.0058, 213.9019: 1913.4573, 227.2116: 1908.3481, 267.4484: 1908.3481, 267.4485: 1908.1178, 281.0798: 1903.1376, 308.5875: 1364.2771, 322.3981: 1355.1738, 407.3496: 1334.6077, 436.4697: 1334.6077, 436.4698: 1326.1887, 451.1147: 1324.0581, 586.6172: 1324.0581}"/>
		<Output spanningTreeLength="1343.71" tourCost="2687.421" timeTaken="611.269" costOverTime="{48.5666: 2081.718, 60.8566: 2054.0623, 73.2085: 1407.7988, 110.7783: 1382.9385, 123.4349: 1365.7021, 161.746: 1365.7021, 161.7461: 1364.9962, 377.7929: 1364.9962, 377.793: 1357.6395, 478.9394: 1353.7136, 553.6412: 1353.7136, 553.6413: 1343.7104, 584.6477: 1343.7104}"/>
		<Output spanningTreeLength="1288.292" tourCost="2576.583" timeTaken="612.634" costOverTime="{24.1763: 2054.1982, 36.3331: 1983.1317, 48.5467: 1983.1317, 48.5468: 1981.0963, 73.1726: 1981.0963, 73.1727: 1971.1353, 85.5896: 1433.1053, 98.0535: 1433.1053, 98.0536: 1431.2202, 110.629: 1421.416, 123.2394: 1378.5243, 135.9437: 1368.6516, 161.6075: 1368.3858, 174.5129: 1367.6393, 187.4955: 1362.101, 200.6293: 1360.4891, 213.8537: 1357.2366, 227.0469: 1357.2366, 227.047: 1304.9778, 240.3811: 1297.5293, 253.7575: 1297.2776, 479.6263: 1297.2776, 479.6264: 1289.9916, 539.9618: 1288.2916, 586.0759: 1288.2916}"/>
		<Output spanningTreeLength="1305.847" tourCost="2611.695" timeTaken="612.151" costOverTime="{24.1797: 2458.4847, 36.3365: 2458.4847, 36.3366: 2191.0518, 48.566: 2046.1155, 60.8468: 2009.0089, 73.1962: 2009.0089, 73.1963: 1995.7495, 85.6377: 1991.2898, 98.1444: 1991.2898, 98.1445: 1467.3634, 123.2915: 1467.3634, 123.2916: 1464.5007, 136.0182: 1406.556, 161.7036: 1405.2871, 187.6313: 1402.1103, 200.7372: 1356.2876, 240.4193: 1356.1596, 254.0164: 1337.7585, 267.4509: 1337.7585, 267.451: 1336.6518, 322.0913: 1334.0298, 406.4752: 1334.0298, 406.4753: 1332.2445, 420.7985: 1329.7166, 435.4367: 1311.1534, 494.2313: 1310.7748, 539.4302: 1308.5665, 569.8741: 1305.8473, 585.3355: 1305.8473}"/>
		<Output spanningTreeLength="1335.332" tourCost="2670.664" timeTaken="612.82" costOverTime="{12.0873: 2458.2141, 24.1937: 2129.5051, 36.3545: 2129.5051, 36.3546: 2038.6234, 48.5721: 2038.6234, 48.5722: 2025.1632, 60.8524: 2023.9879, 73.1935: 2003.003, 98.177: 1995.1102, 110.7288: 1433.7, 123.3586: 1432.9763, 174.525: 1380.0113, 200.6703: 1368.9178, 213.846: 1366.3872, 240.3647: 1366.3872, 240.3648: 1366.024, 253.7724: 1360.669, 267.326: 1359.3437, 308.2305: 1359.3437, 308.2306: 1358.7046, 406.5978: 1358.7046, 406.5979: 1353.3768, 420.8428: 1353.3768, 420.8429: 1353.0549, 450.0758: 1353.0549, 450.0759: 1338.7853, 509.7029: 1337.5876, 524.8605: 1337.5876, 524.8606: 1335.3322, 585.8536: 1335.3322}"/>
	</PRMbaseline>
</Benchmark>
