<?xml version="1.0" ?>
<Benchmark terminals="10" timeLimit="600" env="3D/Home_env.dae" robot="3D/Home_robot.dae" runs="15">
	<PotentiallyOptimal spanningTreeLength="1359.025" tourCost="2028.171" timeTaken="604.718"/>
	<LowerBound spanningTreeLength="1201.099" tourCost="2402.198" timeTaken="1"/>
	<Ripple>
		<Output spanningTreeLength="1320.805" tourCost="1789.913" timeTaken="599.063" pruned="33" costOverTime="{26.172: 1466.8068, 45.1006: 1465.7274, 45.1105: 1465.7274, 45.1155: 1452.657, 45.1351: 1452.1819, 63.7695: 1450.2322, 63.7696: 1448.1262, 82.4087: 1447.6806, 82.4088: 1445.564, 100.8879: 1441.0056, 119.8214: 1439.8156, 138.6657: 1417.4002, 157.6512: 1385.8764, 176.5543: 1384.9646, 195.5398: 1384.9646, 195.5399: 1370.8447, 195.54: 1370.7345, 214.6525: 1370.1894, 214.6527: 1370.1894, 214.6528: 1367.4732, 253.2129: 1367.4732, 253.213: 1358.8926, 272.6706: 1356.3562, 292.1792: 1342.1252, 311.8186: 1342.1252, 311.8187: 1336.5783, 311.828: 1335.6083, 331.589: 1335.2969, 371.4704: 1335.2969, 371.4705: 1332.1454, 411.7871: 1328.9405, 452.5843: 1328.2599, 514.5985: 1328.0103, 535.5566: 1321.7642, 599.058: 1321.7642, 599.0581: 1320.8047}"/>
		<Output spanningTreeLength="1306.712" tourCost="1908.378" timeTaken="597.188" pruned="34" costOverTime="{25.9136: 1463.5912, 44.2282: 1463.5912, 44.2331: 1462.9222, 44.2332: 1453.489, 62.6597: 1453.489, 62.6598: 1432.6694, 81.0786: 1432.6694, 81.0787: 1428.3133, 99.9407: 1427.5705, 99.9408: 1417.4513, 99.941: 1417.4048, 118.6611: 1417.4048, 118.6612: 1414.4861, 156.2599: 1413.6372, 175.1338: 1412.5182, 194.1287: 1412.5182, 194.1288: 1366.5522, 232.4493: 1364.5692, 251.7671: 1364.1007, 251.7673: 1360.7182, 271.1347: 1360.7182, 271.1348: 1355.0114, 290.6495: 1355.0114, 290.6496: 1352.0293, 369.7576: 1346.0816, 409.9517: 1346.0816, 409.9518: 1342.6776, 450.5884: 1327.3334, 491.8153: 1321.5602, 512.6476: 1316.7467, 554.5471: 1306.7118, 597.1815: 1306.7118}"/>
		<Output spanningTreeLength="1339.177" tourCost="1941.779" timeTaken="599.819" pruned="30" costOverTime="{26.2203: 2174.7137, 44.6185: 2163.8292, 44.624: 2160.8205, 44.6897: 2160.8205, 44.7007: 2152.7445, 62.9903: 2140.0345, 63.0062: 2132.0204, 81.4302: 2131.6558, 81.4307: 2129.929, 99.9365: 2127.5212, 118.59: 2121.5251, 137.7539: 2119.2856, 137.754: 2112.9363, 137.7544: 2103.6283, 156.7719: 2095.3818, 175.6942: 2084.4847, 214.7078: 1388.6769, 234.1086: 1387.3433, 253.4243: 1386.8583, 253.4244: 1374.3005, 272.8269: 1373.5645, 312.0151: 1373.4844, 312.0152: 1365.2798, 331.7641: 1357.5557, 351.6925: 1355.8483, 391.6124: 1355.0255, 432.1031: 1352.2346, 472.9855: 1350.9029, 515.1603: 1348.9792, 557.2805: 1346.5195, 599.8142: 1339.1772, 599.8144: 1339.1772}"/>
		<Output spanningTreeLength="1366.162" tourCost="2034.813" timeTaken="600.099" pruned="29" costOverTime="{25.7967: 2350.1707, 44.0435: 2350.0952, 44.0486: 2297.845, 44.0592: 2296.1433, 44.0645: 2293.4008, 44.0996: 2293.4008, 44.1095: 2287.8782, 62.4252: 2280.6695, 62.4301: 2259.8871, 62.4453: 2219.5252, 62.4503: 2219.5252, 62.4504: 2213.9208, 81.0459: 2213.9208, 81.046: 2211.636, 81.0461: 2211.5804, 81.0463: 2196.6345, 99.577: 2190.2122, 136.9164: 2190.2122, 136.9165: 2184.8346, 136.9168: 2161.6852, 156.1845: 2161.6852, 156.1846: 2155.7639, 156.1847: 2154.8622, 156.185: 2154.8622, 156.1851: 2150.4138, 175.0822: 2150.2477, 175.0824: 2149.3064, 175.0827: 2137.6434, 213.7482: 2136.5017, 213.7485: 2136.5017, 213.7486: 2130.3713, 252.3535: 2128.5179, 252.354: 2105.8745, 291.2453: 2104.1601, 311.0132: 2094.8209, 331.8263: 2093.1089, 331.8265: 2091.8527, 351.6825: 2091.5272, 351.6827: 2091.2168, 391.9066: 2091.2168, 391.9067: 2090.5771, 412.2147: 2078.4434, 412.2151: 2072.7799, 432.6314: 2070.7587, 453.1281: 2066.7895, 453.1285: 2064.5918, 494.5617: 1447.2681, 494.5618: 1447.2681, 494.5619: 1444.224, 515.4015: 1444.224, 515.4016: 1396.4368, 515.4017: 1396.4368, 515.4066: 1396.1944, 536.4814: 1372.4004, 557.7844: 1370.6739, 557.7845: 1369.3422, 579.1879: 1369.3422, 579.188: 1366.1624, 596.699: 1366.1624}"/>
		<Output spanningTreeLength="1303.645" tourCost="1704.31" timeTaken="598.835" pruned="34" costOverTime="{26.0901: 2284.17, 44.3566: 2275.3156, 44.3567: 2272.5899, 44.3771: 2228.1354, 44.4167: 2228.1354, 44.4263: 2216.7702, 63.0482: 2209.1598, 63.0487: 2202.7612, 81.6582: 2200.4575, 100.4936: 2199.8623, 100.4937: 2174.0179, 100.5089: 2174.0179, 100.509: 2173.3516, 100.5093: 2138.9617, 138.2904: 2138.0337, 138.2906: 2134.4412, 157.6421: 1391.4668, 176.6417: 1389.6725, 176.6418: 1371.2275, 195.7131: 1362.6834, 215.2982: 1362.6834, 215.2983: 1357.0219, 215.2984: 1349.8953, 234.5159: 1346.9796, 253.7545: 1346.4909, 273.1954: 1346.4909, 273.1955: 1345.6218, 292.6623: 1345.6218, 292.6624: 1344.5288, 312.3468: 1342.3034, 332.0548: 1342.0025, 351.8421: 1342.0025, 351.8422: 1338.0075, 391.9288: 1328.4788, 412.1208: 1321.2966, 473.2022: 1309.1149, 514.6003: 1309.1149, 514.6004: 1307.1392, 556.5136: 1304.988, 577.5768: 1303.8823, 598.8307: 1303.8823, 598.8308: 1303.6451}"/>
		<Output spanningTreeLength="1333.724" tourCost="1936.114" timeTaken="600.0" pruned="30" costOverTime="{25.9093: 2206.3532, 44.2965: 2206.3532, 44.3017: 2199.5411, 44.3187: 2199.5411, 44.3188: 2197.4585, 62.8408: 2193.4727, 62.8409: 2191.4987, 81.3411: 2165.8877, 81.361: 2165.8877, 81.3611: 2156.964, 81.3683: 2117.7478, 100.194: 2116.662, 100.1941: 2116.662, 100.1942: 2115.462, 100.1945: 2104.1271, 118.7993: 2099.0145, 137.4704: 2098.1423, 137.4707: 2096.1822, 137.4708: 2091.1533, 156.2657: 2088.9854, 156.2658: 2087.4948, 156.2659: 2087.2272, 175.1795: 2078.1549, 175.1797: 2077.6294, 213.431: 2077.0555, 213.4314: 2061.4513, 232.6468: 2056.7445, 252.7403: 1438.8429, 252.7405: 1438.1804, 291.8169: 1433.2797, 311.5117: 1431.7099, 331.3415: 1430.0358, 371.255: 1354.9554, 391.3876: 1354.5924, 452.4315: 1353.3662, 472.9533: 1353.3662, 472.9534: 1350.8762, 493.6807: 1344.6454, 536.4009: 1335.845, 557.5107: 1333.952, 578.7683: 1333.952, 578.7684: 1333.7239, 599.9998: 1333.7239}"/>
		<Output spanningTreeLength="1327.928" tourCost="1938.249" timeTaken="599.899" pruned="31" costOverTime="{25.9835: 2649.8355, 25.9836: 2638.8363, 25.9837: 2478.0857, 44.4399: 2477.4791, 44.445: 2473.9127, 44.4452: 2437.9291, 44.4618: 2437.9291, 44.4619: 2396.4305, 63.0677: 2396.4305, 63.0678: 2391.2127, 63.0679: 2376.1487, 63.0837: 2375.4611, 63.0838: 2375.4611, 63.0839: 2368.9477, 63.0841: 2363.6042, 81.8432: 2363.6042, 81.8433: 2356.4213, 81.8485: 2346.3026, 81.8487: 2344.354, 100.7198: 2344.354, 100.7199: 2340.4551, 100.72: 2337.7636, 100.7208: 2337.7636, 100.7209: 2325.5638, 119.3124: 2159.9789, 138.0547: 2158.8032, 156.8932: 2158.8032, 156.8933: 2156.2533, 195.0388: 2151.159, 195.0392: 2128.7573, 214.1611: 2120.3428, 233.7054: 2118.2731, 253.0891: 2118.2731, 253.0892: 1436.9747, 292.4792: 1436.9747, 292.4793: 1387.6267, 312.1387: 1386.9279, 351.7857: 1386.1802, 371.8601: 1380.5921, 391.9732: 1380.5921, 391.9733: 1363.2296, 432.6793: 1356.7146, 453.0718: 1355.8252, 494.3736: 1346.4603, 515.1657: 1336.7443, 536.2326: 1335.1289, 557.2601: 1329.5458, 578.4435: 1327.9277, 599.8943: 1327.9277}"/>
		<Output spanningTreeLength="1319.741" tourCost="1789.826" timeTaken="586.178" pruned="33" costOverTime="{52.2331: 1584.6185, 70.6829: 1584.6185, 70.6879: 1493.028, 89.3769: 1477.9492, 108.1766: 1477.1716, 108.1767: 1436.5785, 126.8929: 1436.5785, 126.893: 1436.2001, 145.6285: 1416.6818, 145.6286: 1409.8241, 164.7404: 1388.7252, 183.8285: 1387.5298, 183.8287: 1385.8638, 202.8622: 1372.5027, 241.1714: 1361.9412, 241.1715: 1356.4646, 260.5416: 1346.098, 279.9518: 1345.0485, 319.2095: 1336.9592, 339.0068: 1334.7637, 358.8612: 1328.7141, 378.8206: 1328.7141, 378.8207: 1325.7403, 399.1723: 1322.8882, 480.9053: 1321.0173, 501.5753: 1320.6224, 522.5697: 1319.7415, 586.1735: 1319.7415}"/>
		<Output spanningTreeLength="1313.39" tourCost="1726.585" timeTaken="597.801" pruned="33" costOverTime="{25.7765: 2268.0309, 44.2182: 2257.7387, 44.2234: 2236.7714, 44.2969: 2236.7714, 44.307: 2224.0081, 62.6532: 2223.4994, 62.6534: 2220.1764, 62.6587: 2220.1764, 62.6588: 2198.5816, 81.052: 2198.5816, 81.0524: 2194.4309, 81.0529: 2184.7166, 99.6668: 2167.5198, 118.2628: 2151.0242, 118.263: 2128.1712, 136.9885: 2127.1664, 136.9889: 2121.3705, 174.7353: 2119.6009, 174.7354: 1447.915, 193.7866: 1447.698, 193.7867: 1438.5523, 212.8538: 1438.5311, 212.8539: 1437.8907, 232.0554: 1400.1922, 270.81: 1397.2186, 290.3369: 1365.667, 310.0185: 1347.905, 310.0186: 1347.8268, 329.6999: 1345.8637, 369.9448: 1344.6393, 390.0495: 1334.0082, 430.6985: 1323.3966, 471.5367: 1322.2297, 512.827: 1321.0879, 533.7544: 1320.9737, 575.8366: 1314.9841, 597.7962: 1314.9841, 597.7963: 1313.3896}"/>
		<Output spanningTreeLength="1299.611" tourCost="1896.551" timeTaken="597.782" pruned="34" costOverTime="{25.9884: 1585.9036, 44.3441: 1585.9036, 44.3684: 1558.859, 62.7291: 1536.0373, 62.7436: 1536.0373, 62.7437: 1412.1259, 81.1341: 1392.1626, 99.6229: 1382.8208, 118.3588: 1379.2055, 118.3589: 1379.2055, 118.359: 1374.5379, 137.0306: 1357.0826, 193.58: 1355.0429, 193.5801: 1354.6732, 212.6381: 1352.0275, 232.0605: 1352.0275, 232.0606: 1350.8378, 290.1575: 1349.3737, 330.0024: 1349.3737, 330.0025: 1331.1069, 350.2351: 1329.1331, 350.2353: 1327.329, 370.2425: 1307.1809, 390.2832: 1302.1543, 390.2833: 1302.1543, 390.2882: 1299.6107, 597.7776: 1299.6107}"/>
		<Output spanningTreeLength="1313.309" tourCost="1922.676" timeTaken="593.543" pruned="33" costOverTime="{78.08: 1463.5538, 96.795: 1436.6187, 115.4746: 1424.9638, 115.4796: 1422.9865, 134.2327: 1410.7077, 134.2423: 1401.2835, 153.02: 1401.2835, 153.0201: 1400.0028, 153.0202: 1389.3412, 229.1962: 1389.3412, 229.1963: 1382.0067, 248.4937: 1376.7356, 248.4938: 1371.9715, 287.3898: 1371.7201, 287.3899: 1354.1061, 307.0245: 1342.3306, 307.0246: 1341.8582, 366.5808: 1339.7679, 406.6787: 1334.628, 406.6788: 1333.6059, 467.8815: 1333.5495, 488.5282: 1333.4618, 529.9945: 1332.5045, 551.1466: 1315.4504, 572.2599: 1313.6425, 593.5379: 1313.309, 593.538: 1313.309}"/>
		<Output spanningTreeLength="1351.116" tourCost="2015.649" timeTaken="602.138" pruned="31" costOverTime="{25.8792: 2383.5637, 62.9506: 2383.5637, 62.9507: 2358.4913, 62.9614: 2315.251, 62.9671: 2315.251, 62.9725: 2308.3677, 81.6274: 2308.3677, 81.6275: 2301.7941, 81.6276: 2301.1889, 81.6278: 2186.7154, 81.6383: 2180.2965, 100.1543: 2166.3068, 100.1595: 2141.5717, 100.1651: 2135.3165, 119.1889: 2135.2317, 137.8957: 2122.0302, 137.8959: 2108.1008, 156.8959: 2097.9502, 214.6216: 2094.8528, 233.9116: 2091.8347, 233.9117: 2086.3245, 253.2315: 2081.125, 272.7607: 2078.8295, 292.5002: 2078.0897, 292.5006: 2077.6544, 313.1089: 2075.798, 333.3219: 2064.6403, 333.322: 2047.443, 333.3326: 2040.8829, 373.5409: 2039.3874, 393.9158: 2038.738, 434.8173: 2038.738, 434.8174: 2038.5219, 476.3156: 1355.7806, 497.1535: 1354.6126, 518.049: 1354.6126, 518.0491: 1353.6378, 539.1239: 1353.6378, 539.124: 1351.1161, 598.9104: 1351.1161}"/>
		<Output spanningTreeLength="1299.921" tourCost="1900.119" timeTaken="599.964" pruned="33" costOverTime="{26.0663: 2270.1747, 44.4036: 2260.6214, 44.4086: 2259.6485, 44.4087: 2259.6485, 44.4088: 2221.3618, 44.4293: 2189.3203, 62.8343: 2188.7118, 62.8344: 2185.4887, 62.8346: 2178.1122, 81.3078: 2178.1122, 81.3079: 2166.7896, 99.7856: 2163.7793, 99.7857: 2160.0337, 99.7908: 2160.0337, 99.7909: 2158.0041, 119.235: 2150.2376, 119.2354: 2150.2376, 119.2355: 2123.9178, 137.9189: 2120.3571, 137.9194: 2116.265, 176.0236: 2115.6268, 195.3284: 2105.7538, 214.9557: 1444.8244, 234.8297: 1444.8244, 234.8298: 1443.5343, 254.2302: 1443.5343, 254.2303: 1441.2485, 273.5926: 1439.1563, 293.122: 1429.9736, 312.7804: 1417.6307, 332.5181: 1409.3499, 352.4706: 1369.3144, 372.5061: 1367.6217, 392.5441: 1366.5101, 392.5442: 1359.5781, 412.7972: 1358.9366, 412.7973: 1357.539, 433.1737: 1355.7421, 453.5799: 1350.3346, 474.1149: 1342.2629, 536.4472: 1309.2459, 557.4839: 1309.2459, 557.484: 1303.7255, 578.6565: 1300.9033, 599.9593: 1299.9209, 599.9594: 1299.9209}"/>
		<Output spanningTreeLength="1292.421" tourCost="1897.771" timeTaken="596.379" pruned="35" costOverTime="{25.8784: 1437.301, 44.1969: 1432.9479, 44.2017: 1430.8142, 44.2067: 1430.8142, 44.2068: 1428.43, 44.2118: 1428.43, 44.2308: 1427.7376, 62.5061: 1427.7376, 62.5062: 1424.8893, 80.8524: 1424.8893, 80.8525: 1423.7651, 80.8572: 1423.7651, 80.8573: 1422.1669, 99.4245: 1420.5024, 117.9422: 1408.4769, 155.3472: 1396.832, 174.427: 1385.3926, 193.3602: 1383.7496, 231.594: 1328.5559, 250.9731: 1327.6465, 289.8841: 1316.8589, 289.8887: 1314.9835, 309.4513: 1314.9397, 349.1131: 1313.8221, 369.0268: 1307.638, 389.0852: 1298.8797, 449.9514: 1294.5305, 470.4236: 1292.8596, 575.0882: 1292.421, 596.375: 1292.421}"/>
		<Output spanningTreeLength="1288.155" tourCost="1687.423" timeTaken="596.71" pruned="34" costOverTime="{25.9626: 1427.2092, 44.3477: 1426.4474, 44.3527: 1425.2093, 44.3583: 1425.0753, 44.3689: 1425.0753, 44.3949: 1423.1375, 62.6906: 1423.0401, 62.6907: 1415.3386, 62.7005: 1393.0069, 62.7101: 1389.681, 81.2042: 1389.681, 81.2043: 1389.6572, 81.2044: 1389.6572, 81.2045: 1387.9846, 99.655: 1385.7109, 99.6551: 1385.6482, 99.6552: 1385.2271, 118.2912: 1380.3465, 118.2913: 1380.3465, 118.2914: 1380.1622, 136.9478: 1380.1622, 136.9479: 1367.4362, 155.7168: 1358.6767, 174.6175: 1352.1958, 193.8948: 1352.1958, 193.8949: 1350.49, 212.9537: 1348.7689, 212.9538: 1348.7689, 212.9539: 1346.0352, 232.075: 1346.0352, 232.0751: 1318.5428, 270.7464: 1317.9427, 290.2299: 1317.9427, 290.23: 1317.8966, 309.8198: 1317.8966, 309.8199: 1316.1239, 329.515: 1314.8358, 369.4184: 1313.6732, 429.9233: 1313.2682, 470.8566: 1306.0093, 554.1807: 1305.264, 575.4266: 1294.6164, 575.4315: 1288.1545, 596.7048: 1288.1545}"/>
	</Ripple>
	<PRMbaseline>
		<Output spanningTreeLength="1348.975" tourCost="2697.951" timeTaken="596.396" costOverTime="{596.3962388038635: 1348.9753774574046}"/>
		<Output spanningTreeLength="1393.495" tourCost="2786.989" timeTaken="597.329" costOverTime="{597.329493522644: 1393.4945335015818}"/>
		<Output spanningTreeLength="1374.366" tourCost="2748.731" timeTaken="596.049" costOverTime="{596.0486958026886: 1374.3656573001845}"/>
		<Output spanningTreeLength="1374.645" tourCost="2749.29" timeTaken="596.374" costOverTime="{596.3739743232727: 1374.6451203430936}"/>
		<Output spanningTreeLength="1365.81" tourCost="2731.621" timeTaken="596.754" costOverTime="{596.753790140152: 1365.8104695307886}"/>
		<Output spanningTreeLength="1390.83" tourCost="2781.66" timeTaken="595.711" costOverTime="{595.7114768028259: 1390.8300829627467}"/>
		<Output spanningTreeLength="1405.241" tourCost="2810.483" timeTaken="597.096" costOverTime="{597.0962641239166: 1405.2414113105974}"/>
		<Output spanningTreeLength="1391.242" tourCost="2782.485" timeTaken="596.173" costOverTime="{596.1727805137634: 1391.2423922444327}"/>
		<Output spanningTreeLength="1338.4" tourCost="2676.8" timeTaken="596.785" costOverTime="{596.7850015163422: 1338.4001777004678}"/>
		<Output spanningTreeLength="1344.065" tourCost="2688.131" timeTaken="596.561" costOverTime="{596.5611293315887: 1344.0652745546004}"/>
		<Output spanningTreeLength="1384.557" tourCost="2769.114" timeTaken="597.546" costOverTime="{597.5456824302673: 1384.556760914064}"/>
		<Output spanningTreeLength="1382.146" tourCost="2764.292" timeTaken="597.152" costOverTime="{597.1521923542023: 1382.1459108282188}"/>
		<Output spanningTreeLength="1410.229" tourCost="2820.459" timeTaken="596.278" costOverTime="{596.278315782547: 1410.2293444437282}"/>
		<Output spanningTreeLength="1362.044" tourCost="2724.088" timeTaken="596.725" costOverTime="{596.7249774932861: 1362.043757488516}"/>
		<Output spanningTreeLength="1414.762" tourCost="2829.525" timeTaken="597.01" costOverTime="{597.0099859237671: 1414.7622581780208}"/>
	</PRMbaseline>
</Benchmark>
