<?xml version="1.0" ?>
<Benchmark terminals="10" timeLimit="600" env="SF/dense_3D.dae" robot="SF/robot_cylinder_small.dae" runs="2" seed="1234">
	<PotentiallyOptimal/>
	<LowerBound spanningTreeLength="4917.408" tourCost="9834.815" timeTaken="1"/>
	<Ripple>
		<Output spanningTreeLength="5217.294" tourCost="5243.025" timeTaken="592.048" pruned="36" ellipsesRemaining="5" costOverTime="{12.935: 5670.8355, 12.9353: 5622.8952, 22.0905: 5622.8952, 22.0906: 5463.2347, 22.0935: 5446.6989, 22.1027: 5373.2719, 31.2245: 5342.0792, 31.2246: 5322.3611, 40.3284: 5322.3611, 40.3285: 5321.7818, 40.3286: 5302.4933, 49.4491: 5287.3321, 58.5861: 5287.3321, 58.5862: 5271.5657, 67.774: 5269.6418, 77.0119: 5262.6108, 86.326: 5257.2483, 95.5331: 5250.5938, 104.7301: 5248.6148, 113.9823: 5247.6165, 141.7738: 5245.5398, 151.0406: 5239.3393, 169.7695: 5239.3393, 169.7696: 5235.6845, 179.1835: 5234.7555, 217.1188: 5232.4044, 255.571: 5231.1114, 284.707: 5230.9711, 353.8481: 5230.2738, 364.0533: 5222.4469, 394.2783: 5217.2941, 592.0241: 5217.2941}"/>
		<Output spanningTreeLength="5234.963" tourCost="5631.413" timeTaken="597.431" pruned="36" ellipsesRemaining="5" costOverTime="{12.8957: 5607.1824, 12.8958: 5599.3079, 22.0273: 5559.5712, 22.0353: 5559.5712, 22.0354: 5472.2729, 31.1458: 5470.6489, 31.1459: 5440.943, 31.146: 5407.296, 40.2721: 5383.9081, 49.4446: 5368.7935, 49.4465: 5311.4439, 58.5671: 5303.7126, 58.5672: 5299.7649, 67.7037: 5295.3898, 67.7038: 5293.1432, 76.8191: 5287.3573, 86.0753: 5287.3573, 86.0754: 5269.7685, 113.6805: 5269.7685, 113.6806: 5248.9968, 122.9425: 5248.8425, 132.2318: 5248.7427, 160.2457: 5248.7427, 160.2458: 5247.2821, 169.6439: 5247.2821, 169.644: 5243.7615, 188.6249: 5243.7615, 188.625: 5242.8276, 217.2161: 5242.8276, 217.2162: 5241.6089, 256.2309: 5241.6089, 256.231: 5238.2764, 285.4106: 5237.5833, 437.3051: 5237.2118, 447.6033: 5235.5012, 479.2277: 5234.9625, 597.384: 5234.9625}"/>
	</Ripple>
	<SFFstar>
		<Output spanningTreeLength="6030.67" tourCost="12061.34" timeTaken="600.001" costOverTime="{600.001: 6030.67}"/>
		<Output spanningTreeLength="6049.67" tourCost="12099.34" timeTaken="600.001" costOverTime="{600.001: 6049.67}"/>
	</SFFstar>
	<MultiTRRT>
		<Output spanningTreeLength="1000000000.0" tourCost="1000000000.0" timeTaken="379.09" costOverTime="{379.09: 1000000000.0}"/>
		<Output spanningTreeLength="1000000000.0" tourCost="1000000000.0" timeTaken="1162.56" costOverTime="{1162.56: 1000000000.0}"/>
	</MultiTRRT>
</Benchmark>
