<?xml version="1.0" ?>
<Benchmark terminals="10" timeLimit="450" env="3D/Apartment_env.dae" robot="3D/Apartment_robot.dae" runs="10">
	<Sstar ordering="UB - LB" informed="True">
		<Output spanningTreeLength="444.965" tourCost="889.931" timeTaken="450" costOverTime="{15.1433: 488.0852, 28.6058: 488.0852, 29.1512: 447.8968, 134.3862: 447.8968, 137.5302: 445.8402, 151.0669: 445.8402, 154.5795: 445.6451, 240.5783: 445.6451, 245.749: 445.4912, 339.8548: 445.4912, 346.7442: 444.9653, 447.6575: 444.9653}"/>
		<Output spanningTreeLength="441.571" tourCost="883.143" timeTaken="450" costOverTime="{15.0327: 453.2365, 28.5473: 453.2365, 29.1374: 446.3717, 42.4736: 446.3717, 43.4188: 441.581, 316.8781: 441.581, 323.3694: 441.5714, 444.41: 441.5714}"/>
		<Output spanningTreeLength="438.306" tourCost="876.612" timeTaken="450" costOverTime="{14.9904: 446.8538, 28.4632: 446.8538, 29.328: 439.8664, 42.6981: 439.8664, 43.7663: 438.3061, 442.2285: 438.3061}"/>
		<Output spanningTreeLength="439.237" tourCost="878.474" timeTaken="450" costOverTime="{14.9591: 443.4674, 28.4285: 443.4674, 28.9815: 440.2652, 364.6164: 440.2652, 372.1329: 439.2372, 439.7889: 439.2372}"/>
		<Output spanningTreeLength="446.845" tourCost="893.691" timeTaken="450" costOverTime="{15.0796: 474.2617, 28.7252: 474.2617, 29.5806: 449.0635, 57.0529: 449.0635, 58.246: 448.163, 71.6163: 448.163, 73.154: 447.5012, 166.4295: 447.5012, 169.9027: 447.3247, 332.8455: 447.3247, 339.2656: 446.8454, 445.6698: 446.8454}"/>
		<Output spanningTreeLength="438.97" tourCost="877.941" timeTaken="450" costOverTime="{15.0494: 442.4046, 28.5223: 442.4046, 29.3889: 438.9703, 436.9111: 438.9703}"/>
		<Output spanningTreeLength="441.634" tourCost="883.268" timeTaken="450" costOverTime="{15.0002: 455.7739, 28.4633: 455.7739, 28.9704: 441.7109, 56.9292: 441.7109, 58.2142: 441.634, 443.3929: 441.634}"/>
		<Output spanningTreeLength="437.427" tourCost="874.854" timeTaken="450" costOverTime="{15.0291: 472.376, 28.4768: 472.376, 29.3543: 440.4082, 42.6995: 440.4082, 43.6423: 437.4268, 441.5373: 437.4268}"/>
		<Output spanningTreeLength="442.968" tourCost="885.937" timeTaken="450" costOverTime="{15.011: 445.4961, 28.4567: 445.4961, 29.0091: 445.2732, 56.5499: 445.2732, 58.0617: 444.795, 71.4011: 444.795, 72.9359: 443.0347, 101.7059: 443.0347, 103.9357: 442.9683, 443.0843: 442.9683}"/>
		<Output spanningTreeLength="439.561" tourCost="879.121" timeTaken="450" costOverTime="{15.1042: 455.1763, 28.58: 455.1763, 29.1315: 441.0089, 56.7462: 441.0089, 58.2661: 440.8367, 86.6151: 440.8367, 88.7287: 439.5698, 185.1224: 439.5698, 189.3058: 439.5607, 449.5132: 439.5607}"/>
	</Sstar>
	<PotentiallyOptimal spanningTreeLength="439.845" tourCost="750.133" timeTaken="452.675"/>
	<LowerBound spanningTreeLength="425.661" tourCost="851.322" timeTaken="1"/>
	<Ripple>
		<Output spanningTreeLength="444.965" tourCost="889.931" timeTaken="450" costOverTime="{14.9844: 488.0852, 28.4468: 488.0852, 28.6831: 447.8968, 124.0606: 447.8968, 124.3433: 445.8402, 137.88: 445.8402, 138.1395: 445.6451, 207.2458: 445.6451, 207.5021: 445.4912, 277.5567: 445.4912, 277.8318: 444.9653, 449.8217: 444.9653}"/>
		<Output spanningTreeLength="441.571" tourCost="883.143" timeTaken="450" costOverTime="{14.9923: 453.2365, 28.5068: 453.2365, 28.7337: 446.3717, 42.0699: 446.3717, 42.3529: 441.581, 262.686: 441.581, 262.9018: 441.5714, 449.3726: 441.5714}"/>
		<Output spanningTreeLength="438.306" tourCost="876.612" timeTaken="450" costOverTime="{15.0055: 446.8538, 28.4782: 446.8538, 28.7009: 439.8664, 42.0709: 439.8664, 42.416: 438.3061, 438.8251: 438.3061}"/>
		<Output spanningTreeLength="439.237" tourCost="878.474" timeTaken="450" costOverTime="{14.9312: 443.4674, 28.4006: 443.4674, 28.636: 440.2652, 292.0051: 440.2652, 292.3109: 439.2372, 449.6538: 439.2372}"/>
		<Output spanningTreeLength="446.104" tourCost="892.208" timeTaken="450" costOverTime="{14.9678: 474.2617, 28.6134: 474.2617, 28.7987: 449.0635, 55.7153: 449.0635, 55.9738: 448.163, 69.344: 448.163, 69.5999: 447.5012, 151.5985: 447.5012, 151.8544: 447.3247, 277.3547: 447.3247, 277.6161: 446.8454, 363.0561: 446.8454, 363.0562: 446.104, 449.8681: 446.104}"/>
		<Output spanningTreeLength="438.97" tourCost="877.941" timeTaken="450" costOverTime="{14.9777: 442.4046, 28.4506: 442.4046, 28.7131: 438.9703, 436.7818: 438.9703}"/>
		<Output spanningTreeLength="441.634" tourCost="883.268" timeTaken="450" costOverTime="{14.9417: 455.7739, 28.4047: 455.7739, 28.6243: 441.7109, 55.6545: 441.7109, 55.9076: 441.634, 438.601: 441.634}"/>
		<Output spanningTreeLength="437.427" tourCost="874.854" timeTaken="450" costOverTime="{14.9271: 472.376, 28.3748: 472.376, 28.6317: 440.4082, 41.9769: 440.4082, 42.264: 437.4268, 438.3399: 437.4268}"/>
		<Output spanningTreeLength="442.968" tourCost="885.937" timeTaken="450" costOverTime="{14.9381: 445.4961, 28.3838: 445.4961, 28.6022: 445.2732, 55.4503: 445.2732, 55.7354: 444.795, 69.0747: 444.795, 69.2917: 443.0347, 96.3581: 443.0347, 96.624: 442.9683, 449.4069: 442.9683}"/>
		<Output spanningTreeLength="439.561" tourCost="879.121" timeTaken="450" costOverTime="{15.0019: 455.1763, 28.4777: 455.1763, 28.6841: 441.0089, 55.6431: 441.0089, 55.9071: 440.8367, 82.8886: 440.8367, 83.1379: 439.5698, 165.3567: 439.5698, 165.5771: 439.5607, 449.941: 439.5607}"/>
	</Ripple>
</Benchmark>
