<?xml version="1.0" ?>
<Benchmark terminals="50" timeLimit="600" env="3D/Abstract_env.dae" robot="3D/Abstract_robot.dae" runs="2" seed="1234">
	<PotentiallyOptimal/>
	<LowerBound spanningTreeLength="3667.98" tourCost="7335.961" timeTaken="1"/>
	<Ripple>
		<Output spanningTreeLength="3753.793" tourCost="4256.207" timeTaken="600.8" pruned="1168" ellipsesRemaining="15" costOverTime="{12.867: 4041.621, 12.8676: 3994.6589, 12.8678: 3954.2684, 12.8777: 3954.2684, 12.9055: 3933.201, 13.0843: 3932.8902, 25.7636: 3932.8902, 25.7643: 3925.4225, 25.8007: 3912.505, 25.8289: 3907.4898, 25.829: 3893.0987, 25.8291: 3893.0987, 25.8412: 3883.4092, 25.8485: 3839.3604, 25.8607: 3839.3604, 25.8631: 3837.4941, 34.9488: 3837.4941, 34.9495: 3817.1811, 34.9527: 3795.6145, 34.9573: 3795.6145, 34.9578: 3795.3718, 34.959: 3795.3718, 34.9592: 3794.9209, 44.0105: 3794.9209, 44.0111: 3787.522, 44.0163: 3787.522, 44.0168: 3781.4346, 44.0178: 3781.4346, 44.018: 3781.2929, 53.0602: 3781.2929, 53.0608: 3775.782, 62.1381: 3775.782, 62.1393: 3775.7259, 71.2558: 3775.7259, 71.257: 3775.4797, 89.5571: 3775.4797, 89.5579: 3773.0439, 98.9907: 3773.0439, 98.9922: 3772.3187, 98.9962: 3772.3187, 98.9971: 3755.9138, 108.154: 3755.9138, 108.1552: 3754.8724, 126.594: 3754.8724, 126.5953: 3754.4935, 369.7294: 3754.4935, 369.7307: 3754.4856, 495.1484: 3754.4856, 495.1497: 3753.7933, 599.6472: 3753.7933}"/>
		<Output spanningTreeLength="3750.093" tourCost="4303.949" timeTaken="596.247" pruned="1171" ellipsesRemaining="13" costOverTime="{13.159: 4005.8607, 13.2489: 3933.9217, 13.4339: 3905.517, 13.5473: 3897.8976, 29.0961: 3897.8976, 29.0968: 3863.6215, 29.1432: 3863.6215, 29.1836: 3819.1152, 29.1999: 3819.1152, 29.2131: 3797.803, 29.2469: 3797.803, 29.2749: 3786.5997, 38.331: 3786.5997, 38.3316: 3783.4007, 38.3352: 3783.4007, 38.3365: 3775.0858, 38.3375: 3775.0858, 38.338: 3768.0596, 47.4298: 3768.0596, 47.4309: 3767.912, 56.5183: 3767.912, 56.5195: 3766.1821, 56.5205: 3766.1821, 56.5209: 3760.512, 75.1321: 3760.512, 75.1323: 3755.5883, 75.1429: 3755.5883, 75.1436: 3753.466, 93.4387: 3753.466, 93.4391: 3751.7301, 102.5661: 3751.7301, 102.5668: 3751.7226, 120.8458: 3751.7226, 120.8464: 3751.0218, 157.6622: 3751.0218, 157.6626: 3750.3701, 157.6645: 3750.3701, 157.6654: 3750.3563, 185.4456: 3750.3563, 185.4464: 3750.2559, 288.9162: 3750.2559, 288.9168: 3750.0928, 595.0295: 3750.0928}"/>
	</Ripple>
	<SFFstar>
		<Output spanningTreeLength="1000000000.0" tourCost="1000000000.0" timeTaken="600.006" costOverTime="{600.006: 1000000000.0}"/>
		<Output spanningTreeLength="1000000000.0" tourCost="1000000000.0" timeTaken="600.0" costOverTime="{600.0: 1000000000.0}"/>
	</SFFstar>
	<MultiTRRT>
		<Output spanningTreeLength="1000000000.0" tourCost="1000000000.0" timeTaken="610" costOverTime="{610: 1000000000.0}"/>
		<Output spanningTreeLength="1000000000.0" tourCost="1000000000.0" timeTaken="610" costOverTime="{610: 1000000000.0}"/>
	</MultiTRRT>
</Benchmark>
